rtl/common/rv32i_params.vh
`ifndef RV32I_PARAMS_VH
`define RV32I_PARAMS_VH

//==============================================================
// File        : rv32i_params.vh
// Description :
//   Global architectural parameters for the RV32I processor.
//
//   This file contains processor-wide constants that are shared
//   across multiple RTL modules.
//
//==============================================================

///////////////////////////////////////////////////////////////
// Processor Configuration
///////////////////////////////////////////////////////////////

`define XLEN                32
`define REG_COUNT           32
`define REG_ADDR_WIDTH      5

///////////////////////////////////////////////////////////////
// Program Counter
///////////////////////////////////////////////////////////////

`define RESET_VECTOR        32'h00000000
`define INSTRUCTION_SIZE    32'd4

///////////////////////////////////////////////////////////////
// Instruction Memory
///////////////////////////////////////////////////////////////

`define IMEM_DEPTH          1024

///////////////////////////////////////////////////////////////
// Data Memory
///////////////////////////////////////////////////////////////

`define DMEM_DEPTH          1024

///////////////////////////////////////////////////////////////
// SHA-256 Accelerator
///////////////////////////////////////////////////////////////

`define SHA_BLOCK_WIDTH     512
`define SHA_HASH_WIDTH      256

///////////////////////////////////////////////////////////////
// General Constants
///////////////////////////////////////////////////////////////

`define TRUE               1'b1
`define FALSE              1'b0

`endif

rtl/core/program_counter.v
`default_nettype none

`include "rv32i_params.vh"

//==============================================================
// Module      : program_counter
// Description :
//   Program Counter (PC) for the RV32I processor.
//
// Features:
//   - Parameterized data width
//   - Synchronous reset
//   - Synchronous write enable
//   - External next PC input
//
// Notes:
//   - The Program Counter does NOT calculate the next address.
//   - The next PC value is generated by the datapath/control
//     logic and supplied through the 'pc_next' input.
//   - This design supports future branch, jump, and pipeline
//     extensions without modification.
//
// Target FPGA : Xilinx Artix-7 (Basys-3)
//==============================================================

module program_counter #(
    parameter DATA_WIDTH = 32
)(
    //----------------------------------------------------------
    // Clock and Reset
    //----------------------------------------------------------

    input  wire                  clk,
    input  wire                  rst,

    //----------------------------------------------------------
    // Control
    //----------------------------------------------------------

    input  wire                  pc_write,

    //----------------------------------------------------------
    // Next Program Counter
    //----------------------------------------------------------

    input  wire [DATA_WIDTH-1:0] pc_next,

    //----------------------------------------------------------
    // Current Program Counter
    //----------------------------------------------------------

    output reg  [DATA_WIDTH-1:0] pc
);

    //----------------------------------------------------------
    // Program Counter Register
    //----------------------------------------------------------

    always @(posedge clk) begin

        if (rst) begin

            pc <= `RESET_VECTOR;

        end

        else if (pc_write) begin

            pc <= pc_next;

        end

    end

endmodule

`default_nettype wire

tb/core/program_counter_tb.v
`timescale 1ns/1ps
`default_nettype none

`include "rv32i_params.vh"

//==============================================================
// Module      : program_counter_tb
// Description :
//   Self-checking verification environment for the
//   RV32I Program Counter.
//
// Features:
//   - Clock generation
//   - Reset verification
//   - Write enable verification
//   - Consecutive PC updates
//   - Hold functionality
//   - Automatic PASS/FAIL reporting
//
//==============================================================

module program_counter_tb;

    //----------------------------------------------------------
    // Parameters
    //----------------------------------------------------------

    parameter DATA_WIDTH = 32;

    //----------------------------------------------------------
    // DUT Signals
    //----------------------------------------------------------

    reg                     clk;
    reg                     rst;
    reg                     pc_write;

    reg  [DATA_WIDTH-1:0]   pc_next;

    wire [DATA_WIDTH-1:0]   pc;

    //----------------------------------------------------------
    // Statistics
    //----------------------------------------------------------

    integer tests;
    integer errors;

    //----------------------------------------------------------
    // Device Under Test
    //----------------------------------------------------------

    program_counter DUT (

        .clk      (clk),
        .rst      (rst),

        .pc_write (pc_write),
        .pc_next  (pc_next),

        .pc       (pc)

    );

    //----------------------------------------------------------
    // Clock Generation
    //----------------------------------------------------------

    initial begin

        clk = 1'b0;

        forever #5 clk = ~clk;

    end

    //----------------------------------------------------------
    // Waveform Dump
    //----------------------------------------------------------

    initial begin

        $dumpfile("sim/program_counter/program_counter.vcd");
        $dumpvars(0, program_counter_tb);

    end

    //----------------------------------------------------------
    // Initialize Statistics
    //----------------------------------------------------------

    initial begin

        tests  = 0;
        errors = 0;

    end

    //----------------------------------------------------------
    // TASK : Reset DUT
    //----------------------------------------------------------

    task reset_dut;

    begin

        $display("");
        $display("-----------------------------------------------");
        $display("Resetting DUT");
        $display("-----------------------------------------------");

        rst      = 1'b1;
        pc_write = 1'b0;
        pc_next  = {DATA_WIDTH{1'b0}};

        @(posedge clk);
        @(posedge clk);

        rst = 1'b0;

    end

    endtask

    //----------------------------------------------------------
    // TASK : Update Program Counter
    //----------------------------------------------------------

    task update_pc;

        input [DATA_WIDTH-1:0] next_address;

    begin

        pc_next  = next_address;
        pc_write = 1'b1;

        @(posedge clk);
        @(posedge clk);

        pc_write = 1'b0;

    end

    endtask

    //----------------------------------------------------------
    // TASK : Check Program Counter
    //----------------------------------------------------------

    task check_pc;

        input [DATA_WIDTH-1:0] expected;

    begin

        #1;

        tests = tests + 1;

        if (pc !== expected) begin

            $display("[FAIL] Expected = %h  Got = %h",
                     expected,
                     pc);

            errors = errors + 1;

        end

        else begin

            $display("[PASS] PC = %h",
                     pc);

        end

    end

    endtask

    //----------------------------------------------------------
    // Test Sequence
    //----------------------------------------------------------

    initial begin

        //------------------------------------------------------
        // Initialize Inputs
        //------------------------------------------------------

        rst      = 1'b0;
        pc_write = 1'b0;
        pc_next  = {DATA_WIDTH{1'b0}};

        $display("");
        $display("=================================================");
        $display("      Program Counter Verification");
        $display("=================================================");

        //------------------------------------------------------
        // Reset Test
        //------------------------------------------------------

        reset_dut();

        check_pc(`RESET_VECTOR);

        //------------------------------------------------------
        // Single Update
        //------------------------------------------------------

        $display("");
        $display("Single Update");

        update_pc(32'h00000004);

        check_pc(32'h00000004);

        //------------------------------------------------------
        // Consecutive Updates
        //------------------------------------------------------

        $display("");
        $display("Consecutive Updates");

        update_pc(32'h00000008);
        check_pc(32'h00000008);

        update_pc(32'h0000000C);
        check_pc(32'h0000000C);

        update_pc(32'h00000010);
        check_pc(32'h00000010);

        //------------------------------------------------------
        // Hold Test
        //------------------------------------------------------

        $display("");
        $display("Write Disable");

        pc_next  = 32'hFFFFFFFF;
        pc_write = 1'b0;

        @(posedge clk);

        check_pc(32'h00000010);

        //------------------------------------------------------
        // Reset Again
        //------------------------------------------------------

        $display("");
        $display("Reset After Operation");

        reset_dut();

        check_pc(`RESET_VECTOR);

        //------------------------------------------------------
        // Verification Summary
        //------------------------------------------------------

        $display("");
        $display("=================================================");
        $display("      Program Counter Verification Summary");
        $display("=================================================");
        $display("");

        $display("Tests  : %0d", tests);
        $display("Errors : %0d", errors);

        $display("");

        if (errors == 0) begin

            $display("***********************************************");
            $display("*                                             *");
            $display("*       ALL TESTS PASSED SUCCESSFULLY!        *");
            $display("*                                             *");
            $display("***********************************************");

        end

        else begin

            $display("***********************************************");
            $display("*                                             *");
            $display("*      VERIFICATION FAILED                    *");
            $display("*                                             *");
            $display("*      Errors : %0d                           *", errors);
            $display("*                                             *");
            $display("***********************************************");

        end

        $display("");

        $finish;

    end

endmodule

`default_nettype wire

sim/program_counter/program_counter.vcd
$date
	Fri Aug 07 14:27:02 2026
$end
$version
	Icarus Verilog
$end
$timescale
	1ps
$end
$scope module program_counter_tb $end
$var wire 32 ! pc [31:0] $end
$var reg 1 " clk $end
$var reg 32 # pc_next [31:0] $end
$var reg 1 $ pc_write $end
$var reg 1 % rst $end
$var integer 32 & errors [31:0] $end
$var integer 32 ' tests [31:0] $end
$scope module DUT $end
$var wire 1 " clk $end
$var wire 32 ( pc_next [31:0] $end
$var wire 1 $ pc_write $end
$var wire 1 % rst $end
$var reg 32 ) pc [31:0] $end
$upscope $end
$scope task check_pc $end
$var reg 32 * expected [31:0] $end
$upscope $end
$scope task reset_dut $end
$upscope $end
$scope task update_pc $end
$var reg 32 + next_address [31:0] $end
$upscope $end
$upscope $end
$enddefinitions $end
#0
$dumpvars
bx +
bx *
bx )
b0 (
b0 '
b0 &
1%
0$
b0 #
0"
bx !
$end
#5000
b0 !
b0 )
1"
#10000
0"
#15000
b0 *
0%
1"
#16000
1$
b100 #
b100 (
b100 +
b1 '
#20000
0"
#25000
b100 !
b100 )
1"
#30000
0"
#35000
b100 *
0$
1"
#36000
1$
b1000 #
b1000 (
b1000 +
b10 '
#40000
0"
#45000
b1000 !
b1000 )
1"
#50000
0"
#55000
b1000 *
0$
1"
#56000
1$
b1100 #
b1100 (
b1100 +
b11 '
#60000
0"
#65000
b1100 !
b1100 )
1"
#70000
0"
#75000
b1100 *
0$
1"
#76000
1$
b10000 #
b10000 (
b10000 +
b100 '
#80000
0"
#85000
b10000 !
b10000 )
1"
#90000
0"
#95000
b10000 *
0$
1"
#96000
b11111111111111111111111111111111 #
b11111111111111111111111111111111 (
b101 '
#100000
0"
#105000
1"
#106000
b0 #
b0 (
1%
b110 '
#110000
0"
#115000
b0 !
b0 )
1"
#120000
0"
#125000
b0 *
0%
1"
#126000
b111 '
