rtl/common/rv32i_defs.vh
`ifndef RV32I_DEFS_VH
`define RV32I_DEFS_VH

//--------------------------------------------------------------
// RV32I ALU Operation Codes
//--------------------------------------------------------------

`define ALU_ADD    4'b0000
`define ALU_SUB    4'b0001
`define ALU_AND    4'b0010
`define ALU_OR     4'b0011
`define ALU_XOR    4'b0100
`define ALU_SLL    4'b0101
`define ALU_SRL    4'b0110
`define ALU_SRA    4'b0111
`define ALU_SLT    4'b1000
`define ALU_SLTU   4'b1001
`define ALU_PASS_B 4'b1010

`endif

rtl/core/alu.v
`default_nettype none

`include "../common/rv32i_defs.vh"

//==============================================================
// Module      : alu
// Description :
//   Arithmetic Logic Unit (ALU) for the RV32I processor.
//
// Features:
//   - Parameterized data width
//   - Pure combinational implementation
//   - Arithmetic operations
//   - Logical operations
//   - Shift operations
//   - Comparison operations
//   - Zero flag generation
//
// Supported Operations:
//   - ADD
//   - SUB
//   - AND
//   - OR
//   - XOR
//   - SLL
//   - SRL
//   - SRA
//   - SLT
//   - SLTU
//   - PASS_B
//
// Target FPGA : Xilinx Artix-7 (Basys-3)
//==============================================================

module alu #(
    parameter DATA_WIDTH = 32
)(
    input  wire [DATA_WIDTH-1:0] operand_a,
    input  wire [DATA_WIDTH-1:0] operand_b,

    input  wire [3:0] alu_op,

    output reg  [DATA_WIDTH-1:0] result,
    output wire                  zero
);

    //----------------------------------------------------------
    // ALU Combinational Logic
    //----------------------------------------------------------

    always @(*) begin

        // Default assignment
        result = {DATA_WIDTH{1'b0}};

        case (alu_op)

            //--------------------------------------------------
            // Arithmetic Operations
            //--------------------------------------------------

            `ALU_ADD:
                result = operand_a + operand_b;

            `ALU_SUB:
                result = operand_a - operand_b;

            //--------------------------------------------------
            // Logical Operations
            //--------------------------------------------------

            `ALU_AND:
                result = operand_a & operand_b;

            `ALU_OR:
                result = operand_a | operand_b;

            `ALU_XOR:
                result = operand_a ^ operand_b;

            //--------------------------------------------------
            // Shift Operations
            //--------------------------------------------------

            `ALU_SLL:
                result = operand_a << operand_b[4:0];

            `ALU_SRL:
                result = operand_a >> operand_b[4:0];

            `ALU_SRA:
                result = $signed(operand_a) >>> operand_b[4:0];

            //--------------------------------------------------
            // Comparison Operations
            //--------------------------------------------------

            `ALU_SLT:
                result = ($signed(operand_a) < $signed(operand_b))
                         ? 32'd1
                         : 32'd0;

            `ALU_SLTU:
                result = (operand_a < operand_b)
                         ? 32'd1
                         : 32'd0;

            //--------------------------------------------------
            // Pass Through
            //--------------------------------------------------

            `ALU_PASS_B:
                result = operand_b;

            //--------------------------------------------------
            // Default
            //--------------------------------------------------

            default:
                result = {DATA_WIDTH{1'b0}};

        endcase

    end

    //----------------------------------------------------------
    // Zero Flag
    //----------------------------------------------------------

    assign zero = (result == {DATA_WIDTH{1'b0}});

endmodule

`default_nettype wire

tb/core/alu_tb.v
`timescale 1ns/1ps
`default_nettype none

`include "../../rtl/common/rv32i_defs.vh"

//==============================================================
// Module      : alu_tb
// Project     : FPGA RISC-V SoC with SHA-256 Accelerator
// Description :
//   Self-checking verification environment for the RV32I ALU.
//
// Features:
//   - Directed testing
//   - PASS / FAIL reporting
//   - Zero flag verification
//   - Waveform generation
//   - Final verification summary
//
//==============================================================

module alu_tb;

    //----------------------------------------------------------
    // Parameters
    //----------------------------------------------------------

    parameter DATA_WIDTH = 32;

    //----------------------------------------------------------
    // DUT Signals
    //----------------------------------------------------------

    reg  [DATA_WIDTH-1:0] operand_a;
    reg  [DATA_WIDTH-1:0] operand_b;

    reg  [3:0] alu_op;

    wire [DATA_WIDTH-1:0] result;
    wire                  zero;

    //----------------------------------------------------------
    // Statistics
    //----------------------------------------------------------

    integer errors;
    integer tests;

    //----------------------------------------------------------
    // Device Under Test
    //----------------------------------------------------------

    alu DUT (

        .operand_a (operand_a),
        .operand_b (operand_b),

        .alu_op    (alu_op),

        .result    (result),
        .zero      (zero)

    );

    //----------------------------------------------------------
    // Waveform Dump
    //----------------------------------------------------------

    initial begin

        $dumpfile("sim/alu/alu.vcd");
        $dumpvars(0, alu_tb);

    end;

    //----------------------------------------------------------
    // Initialize Counters
    //----------------------------------------------------------

    initial begin

        errors = 0;
        tests  = 0;

    end

    //----------------------------------------------------------
    // Verification Task
    //----------------------------------------------------------

    task check_operation;

        input [DATA_WIDTH-1:0] a;
        input [DATA_WIDTH-1:0] b;

        input [3:0] operation;

        input [DATA_WIDTH-1:0] expected_result;
        input                  expected_zero;

    begin

        operand_a = a;
        operand_b = b;
        alu_op    = operation;

        #1;

        tests = tests + 1;

        //------------------------------------------------------
        // Result Check
        //------------------------------------------------------

        if(result !== expected_result) begin

            $display("[FAIL] Result");

            $display("        Operand A : %h", a);
            $display("        Operand B : %h", b);
            $display("        ALU Op    : %b", operation);

            $display("        Expected  : %h", expected_result);
            $display("        Received  : %h", result);

            errors = errors + 1;

        end

        else begin

            $display("[PASS] Result");

        end

        //------------------------------------------------------
        // Zero Flag Check
        //------------------------------------------------------

        if(zero !== expected_zero) begin

            $display("[FAIL] Zero Flag");

            $display("        Expected : %b", expected_zero);
            $display("        Received : %b", zero);

            errors = errors + 1;

        end

        else begin

            $display("[PASS] Zero Flag");

        end

        $display("");

    end

    endtask

    //----------------------------------------------------------
    // Test Sequence
    //----------------------------------------------------------

    initial begin

        $display("");
        $display("=================================================");
        $display("          RV32I ALU Verification");
        $display("=================================================");
        $display("");
            //------------------------------------------------------
        // Arithmetic Operations
        //------------------------------------------------------

        $display("-----------------------------------------------");
        $display("Testing Arithmetic Operations");
        $display("-----------------------------------------------");
        $display("");

        //------------------------------------------------------
        // ADD : Simple Addition
        //------------------------------------------------------

        check_operation(
            32'd10,
            32'd20,
            `ALU_ADD,
            32'd30,
            1'b0
        );

        //------------------------------------------------------
        // ADD : Zero Result
        //------------------------------------------------------

        check_operation(
            32'd0,
            32'd0,
            `ALU_ADD,
            32'd0,
            1'b1
        );

        //------------------------------------------------------
        // ADD : Overflow Check
        //------------------------------------------------------
        // NOTE:
        // RV32I ALU does not generate an overflow flag.
        // The expected behavior is natural 32-bit wraparound.
        //------------------------------------------------------

        check_operation(
            32'hFFFFFFFF,
            32'h00000001,
            `ALU_ADD,
            32'h00000000,
            1'b1
        );

        //------------------------------------------------------
        // SUB : Simple Subtraction
        //------------------------------------------------------

        check_operation(
            32'd20,
            32'd10,
            `ALU_SUB,
            32'd10,
            1'b0
        );

        //------------------------------------------------------
        // SUB : Zero Result
        //------------------------------------------------------

        check_operation(
            32'd25,
            32'd25,
            `ALU_SUB,
            32'd0,
            1'b1
        );

        //------------------------------------------------------
        // SUB : Negative Result
        //------------------------------------------------------

        check_operation(
            32'd10,
            32'd20,
            `ALU_SUB,
            32'hFFFFFFF6,
            1'b0
        );

        //------------------------------------------------------
        // Logical Operations
        //------------------------------------------------------

        $display("-----------------------------------------------");
        $display("Testing Logical Operations");
        $display("-----------------------------------------------");
        $display("");

        //------------------------------------------------------
        // AND
        //------------------------------------------------------

        check_operation(
            32'hF0F0F0F0,
            32'hFFFF0000,
            `ALU_AND,
            32'hF0F00000,
            1'b0
        );

        //------------------------------------------------------
        // AND : All Ones
        //------------------------------------------------------

        check_operation(
            32'hFFFFFFFF,
            32'hFFFFFFFF,
            `ALU_AND,
            32'hFFFFFFFF,
            1'b0
        );

        //------------------------------------------------------
        // AND : All Zeros
        //------------------------------------------------------

        check_operation(
            32'hAAAAAAAA,
            32'h55555555,
            `ALU_AND,
            32'h00000000,
            1'b1
        );

        //------------------------------------------------------
        // OR
        //------------------------------------------------------

        check_operation(
            32'hF0F00000,
            32'h0000F0F0,
            `ALU_OR,
            32'hF0F0F0F0,
            1'b0
        );

        //------------------------------------------------------
        // OR : All Zeros
        //------------------------------------------------------

        check_operation(
            32'h00000000,
            32'h00000000,
            `ALU_OR,
            32'h00000000,
            1'b1
        );

        //------------------------------------------------------
        // XOR
        //------------------------------------------------------

        check_operation(
            32'hAAAAAAAA,
            32'h55555555,
            `ALU_XOR,
            32'hFFFFFFFF,
            1'b0
        );

        //------------------------------------------------------
        // XOR : Same Inputs
        //------------------------------------------------------

        check_operation(
            32'h12345678,
            32'h12345678,
            `ALU_XOR,
            32'h00000000,
            1'b1
        );

        //------------------------------------------------------
        // XOR : Mixed Pattern
        //------------------------------------------------------

        check_operation(
            32'hFFFF0000,
            32'h00FFFF00,
            `ALU_XOR,
            32'hFF00FF00,
            1'b0
        );

                //------------------------------------------------------
        // Shift Operations
        //------------------------------------------------------

        $display("-----------------------------------------------");
        $display("Testing Shift Operations");
        $display("-----------------------------------------------");
        $display("");

        //------------------------------------------------------
        // SLL : Shift Left Logical
        //------------------------------------------------------

        check_operation(
            32'h00000001,
            32'd4,
            `ALU_SLL,
            32'h00000010,
            1'b0
        );

        //------------------------------------------------------
        // SLL : Shift by Zero
        //------------------------------------------------------

        check_operation(
            32'h12345678,
            32'd0,
            `ALU_SLL,
            32'h12345678,
            1'b0
        );

        //------------------------------------------------------
        // SLL : Shift by 31
        //------------------------------------------------------

        check_operation(
            32'h00000001,
            32'd31,
            `ALU_SLL,
            32'h80000000,
            1'b0
        );

        //------------------------------------------------------
        // SRL : Shift Right Logical
        //------------------------------------------------------

        check_operation(
            32'h80000000,
            32'd4,
            `ALU_SRL,
            32'h08000000,
            1'b0
        );

        //------------------------------------------------------
        // SRL : Shift by Zero
        //------------------------------------------------------

        check_operation(
            32'h87654321,
            32'd0,
            `ALU_SRL,
            32'h87654321,
            1'b0
        );

        //------------------------------------------------------
        // SRL : Shift by 31
        //------------------------------------------------------

        check_operation(
            32'h80000000,
            32'd31,
            `ALU_SRL,
            32'h00000001,
            1'b0
        );

        //------------------------------------------------------
        // SRA : Positive Number
        //------------------------------------------------------

        check_operation(
            32'h00000020,
            32'd2,
            `ALU_SRA,
            32'h00000008,
            1'b0
        );

        //------------------------------------------------------
        // SRA : Negative Number
        //------------------------------------------------------

        check_operation(
            32'hFFFFFFF0,
            32'd2,
            `ALU_SRA,
            32'hFFFFFFFC,
            1'b0
        );

        //------------------------------------------------------
        // SRA : Shift by Zero
        //------------------------------------------------------

        check_operation(
            32'hFFFFFF80,
            32'd0,
            `ALU_SRA,
            32'hFFFFFF80,
            1'b0
        );

        //------------------------------------------------------
        // Comparison Operations
        //------------------------------------------------------

        $display("-----------------------------------------------");
        $display("Testing Comparison Operations");
        $display("-----------------------------------------------");
        $display("");

        //------------------------------------------------------
        // SLT : True
        //------------------------------------------------------

        check_operation(
            32'd5,
            32'd10,
            `ALU_SLT,
            32'd1,
            1'b0
        );

        //------------------------------------------------------
        // SLT : False
        //------------------------------------------------------

        check_operation(
            32'd20,
            32'd10,
            `ALU_SLT,
            32'd0,
            1'b1
        );

        //------------------------------------------------------
        // SLT : Signed Comparison
        // (-1 < 1)
        //------------------------------------------------------

        check_operation(
            32'hFFFFFFFF,
            32'h00000001,
            `ALU_SLT,
            32'd1,
            1'b0
        );

        //------------------------------------------------------
        // SLTU : Unsigned Comparison
        //------------------------------------------------------

        check_operation(
            32'd5,
            32'd10,
            `ALU_SLTU,
            32'd1,
            1'b0
        );

        //------------------------------------------------------
        // SLTU : False
        //------------------------------------------------------

        check_operation(
            32'd20,
            32'd10,
            `ALU_SLTU,
            32'd0,
            1'b1
        );

        //------------------------------------------------------
        // SLTU : Unsigned Difference
        //------------------------------------------------------
        // 0xFFFFFFFF > 1 (unsigned)
        //------------------------------------------------------

        check_operation(
            32'hFFFFFFFF,
            32'h00000001,
            `ALU_SLTU,
            32'd0,
            1'b1
        );

        //------------------------------------------------------
        // PASS_B
        //------------------------------------------------------

        check_operation(
            32'h12345678,
            32'hCAFEBABE,
            `ALU_PASS_B,
            32'hCAFEBABE,
            1'b0
        );

        //------------------------------------------------------
        // PASS_B : Zero
        //------------------------------------------------------

        check_operation(
            32'hFFFFFFFF,
            32'h00000000,
            `ALU_PASS_B,
            32'h00000000,
            1'b1
        );

                //------------------------------------------------------
        // Verification Summary
        //------------------------------------------------------

        $display("");
        $display("=================================================");
        $display("           ALU Verification Summary");
        $display("=================================================");
        $display("");

        $display("Total Tests Executed : %0d", tests);
        $display("Total Errors         : %0d", errors);
        $display("");

        if (errors == 0) begin

            $display("***********************************************");
            $display("*                                             *");
            $display("*       ALL TESTS PASSED SUCCESSFULLY!        *");
            $display("*                                             *");
            $display("***********************************************");

        end

        else begin

            $display("***********************************************");
            $display("*                                             *");
            $display("*      VERIFICATION FAILED!                   *");
            $display("*                                             *");
            $display("*      Errors Detected : %0d                  *", errors);
            $display("*                                             *");
            $display("***********************************************");

        end

        $display("");
        $display("=================================================");
        $display("            End of Verification");
        $display("=================================================");
        $display("");

        $finish;

    end

endmodule

`default_nettype wire

sim/alu/alu.vcd
$date
	Fri Aug 07 09:36:28 2026
$end
$version
	Icarus Verilog
$end
$timescale
	1ps
$end
$scope module alu_tb $end
$var wire 1 ! zero $end
$var wire 32 " result [31:0] $end
$var reg 4 # alu_op [3:0] $end
$var reg 32 $ operand_a [31:0] $end
$var reg 32 % operand_b [31:0] $end
$var integer 32 & errors [31:0] $end
$var integer 32 ' tests [31:0] $end
$scope module DUT $end
$var wire 4 ( alu_op [3:0] $end
$var wire 32 ) operand_a [31:0] $end
$var wire 32 * operand_b [31:0] $end
$var wire 1 ! zero $end
$var reg 32 + result [31:0] $end
$upscope $end
$scope task check_operation $end
$var reg 32 , a [31:0] $end
$var reg 32 - b [31:0] $end
$var reg 32 . expected_result [31:0] $end
$var reg 1 / expected_zero $end
$var reg 4 0 operation [3:0] $end
$upscope $end
$upscope $end
$enddefinitions $end
#0
$dumpvars
b0 0
0/
b11110 .
b10100 -
b1010 ,
b11110 +
b10100 *
b1010 )
b0 (
b0 '
b0 &
b10100 %
b1010 $
b0 #
b11110 "
0!
$end
#1000
1!
b0 "
b0 +
b0 %
b0 *
b0 $
b0 )
1/
b0 .
b0 -
b0 ,
b1 '
#2000
b1 %
b1 *
b11111111111111111111111111111111 $
b11111111111111111111111111111111 )
b1 -
b11111111111111111111111111111111 ,
b10 '
#3000
0!
b1010 "
b1010 +
b1 #
b1 (
b1010 %
b1010 *
b10100 $
b10100 )
0/
b1010 .
b1 0
b1010 -
b10100 ,
b11 '
#4000
1!
b0 "
b0 +
b11001 %
b11001 *
b11001 $
b11001 )
1/
b0 .
b11001 -
b11001 ,
b100 '
#5000
0!
b11111111111111111111111111110110 "
b11111111111111111111111111110110 +
b10100 %
b10100 *
b1010 $
b1010 )
0/
b11111111111111111111111111110110 .
b10100 -
b1010 ,
b101 '
#6000
0!
b11110000111100000000000000000000 "
b11110000111100000000000000000000 +
b10 #
b10 (
b11111111111111110000000000000000 %
b11111111111111110000000000000000 *
b11110000111100001111000011110000 $
b11110000111100001111000011110000 )
b11110000111100000000000000000000 .
b10 0
b11111111111111110000000000000000 -
b11110000111100001111000011110000 ,
b110 '
#7000
0!
b11111111111111111111111111111111 "
b11111111111111111111111111111111 +
b11111111111111111111111111111111 %
b11111111111111111111111111111111 *
b11111111111111111111111111111111 $
b11111111111111111111111111111111 )
b11111111111111111111111111111111 .
b11111111111111111111111111111111 -
b11111111111111111111111111111111 ,
b111 '
#8000
1!
b0 "
b0 +
b1010101010101010101010101010101 %
b1010101010101010101010101010101 *
b10101010101010101010101010101010 $
b10101010101010101010101010101010 )
1/
b0 .
b1010101010101010101010101010101 -
b10101010101010101010101010101010 ,
b1000 '
#9000
0!
b11110000111100001111000011110000 "
b11110000111100001111000011110000 +
b11 #
b11 (
b1111000011110000 %
b1111000011110000 *
b11110000111100000000000000000000 $
b11110000111100000000000000000000 )
0/
b11110000111100001111000011110000 .
b11 0
b1111000011110000 -
b11110000111100000000000000000000 ,
b1001 '
#10000
1!
b0 "
b0 +
b0 %
b0 *
b0 $
b0 )
1/
b0 .
b0 -
b0 ,
b1010 '
#11000
0!
b11111111111111111111111111111111 "
b11111111111111111111111111111111 +
b100 #
b100 (
b1010101010101010101010101010101 %
b1010101010101010101010101010101 *
b10101010101010101010101010101010 $
b10101010101010101010101010101010 )
0/
b11111111111111111111111111111111 .
b100 0
b1010101010101010101010101010101 -
b10101010101010101010101010101010 ,
b1011 '
#12000
1!
b0 "
b0 +
b10010001101000101011001111000 %
b10010001101000101011001111000 *
b10010001101000101011001111000 $
b10010001101000101011001111000 )
1/
b0 .
b10010001101000101011001111000 -
b10010001101000101011001111000 ,
b1100 '
#13000
0!
b11111111000000001111111100000000 "
b11111111000000001111111100000000 +
b111111111111111100000000 %
b111111111111111100000000 *
b11111111111111110000000000000000 $
b11111111111111110000000000000000 )
0/
b11111111000000001111111100000000 .
b111111111111111100000000 -
b11111111111111110000000000000000 ,
b1101 '
#14000
0!
b10000 "
b10000 +
b101 #
b101 (
b100 %
b100 *
b1 $
b1 )
b10000 .
b101 0
b100 -
b1 ,
b1110 '
#15000
0!
b10010001101000101011001111000 "
b10010001101000101011001111000 +
b0 %
b0 *
b10010001101000101011001111000 $
b10010001101000101011001111000 )
b10010001101000101011001111000 .
b0 -
b10010001101000101011001111000 ,
b1111 '
#16000
0!
b10000000000000000000000000000000 "
b10000000000000000000000000000000 +
b11111 %
b11111 *
b1 $
b1 )
b10000000000000000000000000000000 .
b11111 -
b1 ,
b10000 '
#17000
0!
b1000000000000000000000000000 "
b1000000000000000000000000000 +
b110 #
b110 (
b100 %
b100 *
b10000000000000000000000000000000 $
b10000000000000000000000000000000 )
b1000000000000000000000000000 .
b110 0
b100 -
b10000000000000000000000000000000 ,
b10001 '
#18000
0!
b10000111011001010100001100100001 "
b10000111011001010100001100100001 +
b0 %
b0 *
b10000111011001010100001100100001 $
b10000111011001010100001100100001 )
b10000111011001010100001100100001 .
b0 -
b10000111011001010100001100100001 ,
b10010 '
#19000
0!
b1 "
b1 +
b11111 %
b11111 *
b10000000000000000000000000000000 $
b10000000000000000000000000000000 )
b1 .
b11111 -
b10000000000000000000000000000000 ,
b10011 '
#20000
0!
b1000 "
b1000 +
b111 #
b111 (
b10 %
b10 *
b100000 $
b100000 )
b1000 .
b111 0
b10 -
b100000 ,
b10100 '
#21000
0!
b11111111111111111111111111111100 "
b11111111111111111111111111111100 +
b11111111111111111111111111110000 $
b11111111111111111111111111110000 )
b11111111111111111111111111111100 .
b11111111111111111111111111110000 ,
b10101 '
#22000
0!
b11111111111111111111111110000000 "
b11111111111111111111111110000000 +
b0 %
b0 *
b11111111111111111111111110000000 $
b11111111111111111111111110000000 )
b11111111111111111111111110000000 .
b0 -
b11111111111111111111111110000000 ,
b10110 '
#23000
0!
b1 "
b1 +
b1000 #
b1000 (
b1010 %
b1010 *
b101 $
b101 )
b1 .
b1000 0
b1010 -
b101 ,
b10111 '
#24000
1!
b0 "
b0 +
b10100 $
b10100 )
1/
b0 .
b10100 ,
b11000 '
#25000
0!
b1 "
b1 +
b1 %
b1 *
b11111111111111111111111111111111 $
b11111111111111111111111111111111 )
0/
b1 .
b1 -
b11111111111111111111111111111111 ,
b11001 '
#26000
0!
b1 "
b1 +
b1001 #
b1001 (
b1010 %
b1010 *
b101 $
b101 )
b1001 0
b1010 -
b101 ,
b11010 '
#27000
1!
b0 "
b0 +
b10100 $
b10100 )
1/
b0 .
b10100 ,
b11011 '
#28000
b1 %
b1 *
b11111111111111111111111111111111 $
b11111111111111111111111111111111 )
b1 -
b11111111111111111111111111111111 ,
b11100 '
#29000
0!
b11001010111111101011101010111110 "
b11001010111111101011101010111110 +
b1010 #
b1010 (
b11001010111111101011101010111110 %
b11001010111111101011101010111110 *
b10010001101000101011001111000 $
b10010001101000101011001111000 )
0/
b11001010111111101011101010111110 .
b1010 0
b11001010111111101011101010111110 -
b10010001101000101011001111000 ,
b11101 '
#30000
1!
b0 "
b0 +
b0 %
b0 *
b11111111111111111111111111111111 $
b11111111111111111111111111111111 )
1/
b0 .
b0 -
b11111111111111111111111111111111 ,
b11110 '
#31000
b11111 '
