rtl/core/next_pc.v
`default_nettype none

//==============================================================
// Module      : next_pc
// Project     : FPGA RISC-V SoC with SHA-256 Accelerator
// Description :
//   Selects the next Program Counter value for the RV32I core.
//
//   PC source selection:
//
//     2'b00 -> Sequential execution : PC + 4
//     2'b01 -> Conditional branch
//     2'b10 -> JAL target
//     2'b11 -> JALR target
//
//   The target addresses are calculated outside this module.
//   This module only selects the appropriate target.
//
//==============================================================

module next_pc #(
    parameter DATA_WIDTH = 32
)(
    //----------------------------------------------------------
    // Current Program Counter
    //----------------------------------------------------------

    input wire [DATA_WIDTH-1:0] pc,

    //----------------------------------------------------------
    // Pre-calculated PC Targets
    //----------------------------------------------------------

    input wire [DATA_WIDTH-1:0] branch_target,
    input wire [DATA_WIDTH-1:0] jal_target,
    input wire [DATA_WIDTH-1:0] jalr_target,

    //----------------------------------------------------------
    // Branch Condition
    //----------------------------------------------------------

    input wire                  branch_taken,

    //----------------------------------------------------------
    // PC Source Selection
    //
    // 00 -> PC + 4
    // 01 -> Branch
    // 10 -> JAL
    // 11 -> JALR
    //----------------------------------------------------------

    input wire [1:0]            pc_src,

    //----------------------------------------------------------
    // Next Program Counter
    //----------------------------------------------------------

    output reg [DATA_WIDTH-1:0] next_pc
);

    //----------------------------------------------------------
    // Next-PC Selection Logic
    //----------------------------------------------------------

    always @(*) begin

        case (pc_src)

            //--------------------------------------------------
            // Normal Sequential Execution
            //--------------------------------------------------

            2'b00: begin

                next_pc = pc + {{(DATA_WIDTH-3){1'b0}}, 3'b100};

            end

            //--------------------------------------------------
            // Conditional Branch
            //--------------------------------------------------

            2'b01: begin

                if (branch_taken)
                    next_pc = branch_target;
                else
                    next_pc = pc + {{(DATA_WIDTH-3){1'b0}}, 3'b100};

            end

            //--------------------------------------------------
            // JAL
            //--------------------------------------------------

            2'b10: begin

                next_pc = jal_target;

            end

            //--------------------------------------------------
            // JALR
            //--------------------------------------------------

            2'b11: begin

                next_pc = jalr_target;

            end

            //--------------------------------------------------
            // Default
            //
            // This should never be reached because pc_src
            // contains only four possible 2-bit values.
            //--------------------------------------------------

            default: begin

                next_pc = pc + {{(DATA_WIDTH-3){1'b0}}, 3'b100};

            end

        endcase

    end

endmodule

`default_nettype wire

tb/core/next_pc_tb.v
`timescale 1ns/1ps
`default_nettype none

//==============================================================
// Module      : next_pc_tb
// Description :
//   Testbench for the RV32I Next-PC Selection Unit.
//
//   Tests:
//     1. Normal sequential execution
//     2. Branch not taken
//     3. Branch taken
//     4. JAL
//     5. JALR
//
//==============================================================

module next_pc_tb;

    //----------------------------------------------------------
    // Parameters
    //----------------------------------------------------------

    localparam DATA_WIDTH = 32;

    //----------------------------------------------------------
    // Testbench Signals
    //----------------------------------------------------------

    reg [DATA_WIDTH-1:0] pc;

    reg [DATA_WIDTH-1:0] branch_target;
    reg [DATA_WIDTH-1:0] jal_target;
    reg [DATA_WIDTH-1:0] jalr_target;

    reg                  branch_taken;

    reg [1:0]            pc_src;

    wire [DATA_WIDTH-1:0] next_pc;

    //----------------------------------------------------------
    // Test Statistics
    //----------------------------------------------------------

    integer tests;
    integer errors;

    //----------------------------------------------------------
    // Device Under Test
    //----------------------------------------------------------

    next_pc #(
        .DATA_WIDTH(DATA_WIDTH)
    ) DUT (
        .pc           (pc),
        .branch_target(branch_target),
        .jal_target   (jal_target),
        .jalr_target  (jalr_target),
        .branch_taken (branch_taken),
        .pc_src       (pc_src),
        .next_pc      (next_pc)
    );

    //----------------------------------------------------------
    // Waveform Dump
    //----------------------------------------------------------

    initial begin

        $dumpfile("sim/next_pc/next_pc.vcd");
        $dumpvars(0, next_pc_tb);

    end

    //----------------------------------------------------------
    // Check Task
    //----------------------------------------------------------

    task check_next_pc;

        input [31:0] expected;
        input [127:0] test_name;

    begin

        #1;

        tests = tests + 1;

        if (next_pc !== expected) begin

            $display("");
            $display("[FAIL] %s", test_name);

            $display("       PC            = %h", pc);
            $display("       PC Source     = %b", pc_src);
            $display("       Branch Taken  = %b", branch_taken);

            $display("       Expected      = %h", expected);
            $display("       Got           = %h", next_pc);

            errors = errors + 1;

        end

        else begin

            $display("[PASS] %s", test_name);

        end

    end

    endtask

    //----------------------------------------------------------
    // Test Sequence
    //----------------------------------------------------------

    initial begin

        //------------------------------------------------------
        // Initial Values
        //------------------------------------------------------

        pc            = 32'b0;

        branch_target = 32'b0;
        jal_target    = 32'b0;
        jalr_target   = 32'b0;

        branch_taken  = 1'b0;

        pc_src        = 2'b00;

        tests  = 0;
        errors = 0;

        //------------------------------------------------------
        // Header
        //------------------------------------------------------

        $display("");
        $display("=================================================");
        $display("          Next-PC Unit Verification");
        $display("=================================================");

        //------------------------------------------------------
        // TEST 1
        // Normal Sequential Execution
        //
        // PC = 0x100
        // Expected = PC + 4 = 0x104
        //------------------------------------------------------

        pc     = 32'h00000100;
        pc_src = 2'b00;

        check_next_pc(
            32'h00000104,
            "Sequential PC + 4"
        );

        //------------------------------------------------------
        // TEST 2
        // Another Sequential Address
        //------------------------------------------------------

        pc     = 32'h00001000;
        pc_src = 2'b00;

        check_next_pc(
            32'h00001004,
            "Sequential PC + 4 at 0x1000"
        );

        //------------------------------------------------------
        // TEST 3
        // Branch NOT Taken
        //
        // Even though branch_target is available,
        // branch_taken = 0 means continue sequentially.
        //------------------------------------------------------

        pc            = 32'h00000200;
        branch_target = 32'h00000240;

        branch_taken = 1'b0;
        pc_src       = 2'b01;

        check_next_pc(
            32'h00000204,
            "Branch not taken -> PC + 4"
        );

        //------------------------------------------------------
        // TEST 4
        // Branch Taken
        //------------------------------------------------------

        pc            = 32'h00000200;
        branch_target = 32'h00000240;

        branch_taken = 1'b1;
        pc_src       = 2'b01;

        check_next_pc(
            32'h00000240,
            "Branch taken -> branch target"
        );

        //------------------------------------------------------
        // TEST 5
        // JAL
        //------------------------------------------------------

        pc          = 32'h00000300;
        jal_target  = 32'h00001000;

        pc_src = 2'b10;

        check_next_pc(
            32'h00001000,
            "JAL -> JAL target"
        );

        //------------------------------------------------------
        // TEST 6
        // JALR
        //------------------------------------------------------

        pc           = 32'h00000400;
        jalr_target  = 32'h00002000;

        pc_src = 2'b11;

        check_next_pc(
            32'h00002000,
            "JALR -> JALR target"
        );

        //------------------------------------------------------
        // TEST 7
        // Branch Taken with Negative/Backward Target
        //------------------------------------------------------

        pc            = 32'h00001000;
        branch_target = 32'h00000F00;

        branch_taken = 1'b1;
        pc_src       = 2'b01;

        check_next_pc(
            32'h00000F00,
            "Backward branch target"
        );

        //------------------------------------------------------
        // TEST 8
        // JAL to a Lower Address
        //------------------------------------------------------

        pc         = 32'h00002000;
        jal_target = 32'h00001800;

        pc_src = 2'b10;

        check_next_pc(
            32'h00001800,
            "JAL to lower address"
        );

        //------------------------------------------------------
        // TEST 9
        // JALR to a Different Address
        //------------------------------------------------------

        pc          = 32'h00003000;
        jalr_target = 32'h00004004;

        pc_src = 2'b11;

        check_next_pc(
            32'h00004004,
            "JALR target selection"
        );

        //------------------------------------------------------
        // TEST 10
        // Branch Target Should Be Ignored When Not Taken
        //------------------------------------------------------

        pc            = 32'h00005000;
        branch_target = 32'hDEADBEEF;

        branch_taken = 1'b0;
        pc_src       = 2'b01;

        check_next_pc(
            32'h00005004,
            "Not-taken branch ignores target"
        );

        //------------------------------------------------------
        // Summary
        //------------------------------------------------------

        $display("");
        $display("=================================================");
        $display("Verification Summary");
        $display("=================================================");

        $display("Tests  : %0d", tests);
        $display("Errors : %0d", errors);

        $display("");

        if (errors == 0) begin

            $display("***********************************************");
            $display("*                                             *");
            $display("*       ALL TESTS PASSED SUCCESSFULLY!       *");
            $display("*                                             *");
            $display("***********************************************");

        end

        else begin

            $display("***********************************************");
            $display("*                                             *");
            $display("*       VERIFICATION FAILED                   *");
            $display("*                                             *");
            $display("*       Errors : %0d                           *", errors);
            $display("*                                             *");
            $display("***********************************************");

        end

        $finish;

    end

endmodule

`default_nettype wire

sim/next_pc/next_pc.vcd
$date
	Sun Aug 09 10:31:00 2026
$end
$version
	Icarus Verilog
$end
$timescale
	1ps
$end
$scope module next_pc_tb $end
$var wire 32 ! next_pc [31:0] $end
$var reg 1 " branch_taken $end
$var reg 32 # branch_target [31:0] $end
$var reg 32 $ jal_target [31:0] $end
$var reg 32 % jalr_target [31:0] $end
$var reg 32 & pc [31:0] $end
$var reg 2 ' pc_src [1:0] $end
$var integer 32 ( errors [31:0] $end
$var integer 32 ) tests [31:0] $end
$scope module DUT $end
$var wire 1 " branch_taken $end
$var wire 32 * branch_target [31:0] $end
$var wire 32 + jal_target [31:0] $end
$var wire 32 , jalr_target [31:0] $end
$var wire 32 - pc [31:0] $end
$var wire 2 . pc_src [1:0] $end
$var reg 32 / next_pc [31:0] $end
$upscope $end
$scope task check_next_pc $end
$var reg 32 0 expected [31:0] $end
$var reg 128 1 test_name [127:0] $end
$upscope $end
$upscope $end
$enddefinitions $end
#0
$dumpvars
b1100101011100010111010101100101011011100111010001101001011000010110110000100000010100000100001100100000001010110010000000110100 1
b100000100 0
b100000100 /
b0 .
b100000000 -
b0 ,
b0 +
b0 *
b0 )
b0 (
b0 '
b100000000 &
b0 %
b0 $
b0 #
0"
b100000100 !
$end
#1000
b1000000000100 !
b1000000000100 /
b1010000010000110010000000101011001000000011010000100000011000010111010000100000001100000111100000110001001100000011000000110000 1
b1000000000100 0
b1000000000000 &
b1000000000000 -
b1 )
#2000
b1000000100 !
b1000000100 /
b100000011101000110000101101011011001010110111000100000001011010011111000100000010100000100001100100000001010110010000000110100 1
b1000000100 0
b1 '
b1 .
b1001000000 #
b1001000000 *
b1000000000 &
b1000000000 -
b10 )
#3000
b1001000000 !
b1001000000 /
b101101001111100010000001100010011100100110000101101110011000110110100000100000011101000110000101110010011001110110010101110100 1
b1001000000 0
1"
b11 )
#4000
b1000000000000 !
b1000000000000 /
b1000001010011000010000000101101001111100010000001001010010000010100110000100000011101000110000101110010011001110110010101110100 1
b1000000000000 0
b10 '
b10 .
b1000000000000 $
b1000000000000 +
b1100000000 &
b1100000000 -
b100 )
#5000
b10000000000000 !
b10000000000000 /
b1010010001000000010110100111110001000000100101001000001010011000101001000100000011101000110000101110010011001110110010101110100 1
b10000000000000 0
b11 '
b11 .
b10000000000000 %
b10000000000000 ,
b10000000000 &
b10000000000 -
b101 )
#6000
b111100000000 !
b111100000000 /
b1110010011001000010000001100010011100100110000101101110011000110110100000100000011101000110000101110010011001110110010101110100 1
b111100000000 0
b1 '
b1 .
b111100000000 #
b111100000000 *
b1000000000000 &
b1000000000000 -
b110 )
#7000
b1100000000000 !
b1100000000000 /
b1110100011011110010000001101100011011110111011101100101011100100010000001100001011001000110010001110010011001010111001101110011 1
b1100000000000 0
b10 '
b10 .
b1100000000000 $
b1100000000000 +
b10000000000000 &
b10000000000000 -
b111 )
#8000
b100000000000100 !
b100000000000100 /
b1110100011000010111001001100111011001010111010000100000011100110110010101101100011001010110001101110100011010010110111101101110 1
b100000000000100 0
b11 '
b11 .
b100000000000100 %
b100000000000100 ,
b11000000000000 &
b11000000000000 -
b1000 )
#9000
b101000000000100 !
b101000000000100 /
b1101000001000000110100101100111011011100110111101110010011001010111001100100000011101000110000101110010011001110110010101110100 1
b101000000000100 0
b1 '
b1 .
0"
b11011110101011011011111011101111 #
b11011110101011011011111011101111 *
b101000000000000 &
b101000000000000 -
b1001 )
#10000
b1010 )
