rtl/common/rv32i_defs.vh
`ifndef RV32I_DEFS_VH
`define RV32I_DEFS_VH

//--------------------------------------------------------------
// RV32I ALU Operation Codes
//--------------------------------------------------------------

`define ALU_ADD    4'b0000
`define ALU_SUB    4'b0001
`define ALU_AND    4'b0010
`define ALU_OR     4'b0011
`define ALU_XOR    4'b0100
`define ALU_SLL    4'b0101
`define ALU_SRL    4'b0110
`define ALU_SRA    4'b0111
`define ALU_SLT    4'b1000
`define ALU_SLTU   4'b1001
`define ALU_PASS_B 4'b1010

`define OPCODE_OP_IMM   7'b0010011
`define OPCODE_LOAD     7'b0000011
`define OPCODE_STORE    7'b0100011
`define OPCODE_BRANCH   7'b1100011
`define OPCODE_LUI      7'b0110111
`define OPCODE_AUIPC    7'b0010111
`define OPCODE_JAL      7'b1101111
`define OPCODE_JALR     7'b1100111

`endif

rtl/common/rv32i_params.vh
`ifndef RV32I_PARAMS_VH
`define RV32I_PARAMS_VH

//==============================================================
// File        : rv32i_params.vh
// Description :
//   Global architectural parameters for the RV32I processor.
//
//   This file contains processor-wide constants that are shared
//   across multiple RTL modules.
//
//==============================================================

///////////////////////////////////////////////////////////////
// Processor Configuration
///////////////////////////////////////////////////////////////

`define XLEN                32
`define REG_COUNT           32
`define REG_ADDR_WIDTH      5

///////////////////////////////////////////////////////////////
// Program Counter
///////////////////////////////////////////////////////////////

`define RESET_VECTOR        32'h00000000
`define INSTRUCTION_SIZE    32'd4

///////////////////////////////////////////////////////////////
// Instruction Memory
///////////////////////////////////////////////////////////////

`define IMEM_DEPTH          1024

///////////////////////////////////////////////////////////////
// Data Memory
///////////////////////////////////////////////////////////////

`define DMEM_DEPTH          1024

///////////////////////////////////////////////////////////////
// SHA-256 Accelerator
///////////////////////////////////////////////////////////////

`define SHA_BLOCK_WIDTH     512
`define SHA_HASH_WIDTH      256

///////////////////////////////////////////////////////////////
// General Constants
///////////////////////////////////////////////////////////////

`define TRUE               1'b1
`define FALSE              1'b0

`endif

rtl/core/branch_unit.v
`default_nettype none

`include "rv32i_params.vh"
`include "rv32i_defs.vh"

//==============================================================
// Module      : branch_unit
// Description :
//   Determines whether an RV32I conditional branch condition
//   is satisfied.
//
//   The Branch Unit receives:
//     - funct3   : Identifies the branch condition
//     - rs1_data : First register operand
//     - rs2_data : Second register operand
//
//   It produces:
//     - branch_taken : 1 when the branch condition is satisfied
//
// Supported Branch Instructions:
//     BEQ  - Branch if Equal
//     BNE  - Branch if Not Equal
//     BLT  - Branch if Less Than (signed)
//     BGE  - Branch if Greater Than or Equal (signed)
//     BLTU - Branch if Less Than (unsigned)
//     BGEU - Branch if Greater Than or Equal (unsigned)
//
// Important:
//   This module does NOT calculate the branch target address.
//   It only determines whether the branch condition is true.
//==============================================================

module branch_unit #(
    parameter DATA_WIDTH = 32
)(
    //----------------------------------------------------------
    // Instruction Function Field
    //----------------------------------------------------------

    input wire [2:0] funct3,

    //----------------------------------------------------------
    // Register Operands
    //----------------------------------------------------------

    input wire [DATA_WIDTH-1:0] rs1_data,
    input wire [DATA_WIDTH-1:0] rs2_data,

    //----------------------------------------------------------
    // Branch Decision
    //----------------------------------------------------------

    output reg branch_taken
);

    //----------------------------------------------------------
    // Branch Condition Logic
    //----------------------------------------------------------

    always @(*) begin

        //------------------------------------------------------
        // Safe Default
        //------------------------------------------------------

        branch_taken = 1'b0;

        //------------------------------------------------------
        // Decode Branch Type
        //------------------------------------------------------

        case (funct3)

            //--------------------------------------------------
            // BEQ
            //
            // Branch if rs1 == rs2
            //--------------------------------------------------

            3'b000: begin

                if (rs1_data == rs2_data)
                    branch_taken = 1'b1;

            end

            //--------------------------------------------------
            // BNE
            //
            // Branch if rs1 != rs2
            //--------------------------------------------------

            3'b001: begin

                if (rs1_data != rs2_data)
                    branch_taken = 1'b1;

            end

            //--------------------------------------------------
            // BLT
            //
            // Signed comparison:
            // Branch if rs1 < rs2
            //--------------------------------------------------

            3'b100: begin

                if ($signed(rs1_data) < $signed(rs2_data))
                    branch_taken = 1'b1;

            end

            //--------------------------------------------------
            // BGE
            //
            // Signed comparison:
            // Branch if rs1 >= rs2
            //--------------------------------------------------

            3'b101: begin

                if ($signed(rs1_data) >= $signed(rs2_data))
                    branch_taken = 1'b1;

            end

            //--------------------------------------------------
            // BLTU
            //
            // Unsigned comparison:
            // Branch if rs1 < rs2
            //--------------------------------------------------

            3'b110: begin

                if (rs1_data < rs2_data)
                    branch_taken = 1'b1;

            end

            //--------------------------------------------------
            // BGEU
            //
            // Unsigned comparison:
            // Branch if rs1 >= rs2
            //--------------------------------------------------

            3'b111: begin

                if (rs1_data >= rs2_data)
                    branch_taken = 1'b1;

            end

            //--------------------------------------------------
            // Unsupported funct3
            //--------------------------------------------------

            default: begin

                branch_taken = 1'b0;

            end

        endcase

    end

endmodule

`default_nettype wire

tb/core/branch_unit_tb.v
`timescale 1ns/1ps
`default_nettype none

`include "rv32i_params.vh"
`include "rv32i_defs.vh"

//==============================================================
// Module      : branch_unit_tb
// Description :
//   Basic functional testbench for the RV32I Branch Unit.
//
//   Tests:
//     BEQ
//     BNE
//     BLT
//     BGE
//     BLTU
//     BGEU
//
//==============================================================

module branch_unit_tb;

    //----------------------------------------------------------
    // DUT Inputs
    //----------------------------------------------------------

    reg [2:0]  funct3;

    reg [31:0] rs1_data;
    reg [31:0] rs2_data;

    //----------------------------------------------------------
    // DUT Output
    //----------------------------------------------------------

    wire branch_taken;

    //----------------------------------------------------------
    // Test Statistics
    //----------------------------------------------------------

    integer tests;
    integer errors;

    //----------------------------------------------------------
    // Device Under Test
    //----------------------------------------------------------

    branch_unit DUT (
        .funct3       (funct3),
        .rs1_data     (rs1_data),
        .rs2_data     (rs2_data),
        .branch_taken (branch_taken)
    );

    //----------------------------------------------------------
    // Waveform Dump
    //----------------------------------------------------------

    initial begin

        $dumpfile("sim/branch_unit/branch_unit.vcd");
        $dumpvars(0, branch_unit_tb);

    end

    //----------------------------------------------------------
    // Test Task
    //----------------------------------------------------------

    task check_branch;

        input [2:0]  test_funct3;
        input [31:0] test_rs1;
        input [31:0] test_rs2;
        input        expected;
        input [127:0] test_name;

    begin

        //------------------------------------------------------
        // Apply Inputs
        //------------------------------------------------------

        funct3   = test_funct3;
        rs1_data = test_rs1;
        rs2_data = test_rs2;

        #1;

        tests = tests + 1;

        //------------------------------------------------------
        // Check Result
        //------------------------------------------------------

        if (branch_taken !== expected) begin

            $display("");
            $display("[FAIL] %s", test_name);

            $display("       funct3       = %b", test_funct3);
            $display("       rs1_data     = %h", test_rs1);
            $display("       rs2_data     = %h", test_rs2);
            $display("       Expected    = %b", expected);
            $display("       Actual      = %b", branch_taken);

            errors = errors + 1;

        end

        else begin

            $display("[PASS] %s", test_name);

        end

    end

    endtask

    //----------------------------------------------------------
    // Test Sequence
    //----------------------------------------------------------

    initial begin

        funct3   = 3'b000;
        rs1_data = 32'd0;
        rs2_data = 32'd0;

        tests  = 0;
        errors = 0;

        #5;

        $display("");
        $display("=================================================");
        $display("          Branch Unit Verification");
        $display("=================================================");

        //------------------------------------------------------
        // BEQ
        //------------------------------------------------------

        check_branch(
            3'b000,
            32'd10,
            32'd10,
            1'b1,
            "BEQ - Equal"
        );

        check_branch(
            3'b000,
            32'd10,
            32'd20,
            1'b0,
            "BEQ - Not Equal"
        );

        //------------------------------------------------------
        // BNE
        //------------------------------------------------------

        check_branch(
            3'b001,
            32'd10,
            32'd20,
            1'b1,
            "BNE - Not Equal"
        );

        check_branch(
            3'b001,
            32'd10,
            32'd10,
            1'b0,
            "BNE - Equal"
        );

        //------------------------------------------------------
        // BLT - Signed
        //------------------------------------------------------

        check_branch(
            3'b100,
            32'd10,
            32'd20,
            1'b1,
            "BLT - Less Than"
        );

        check_branch(
            3'b100,
            32'd20,
            32'd10,
            1'b0,
            "BLT - Greater Than"
        );

        //------------------------------------------------------
        // BGE - Signed
        //------------------------------------------------------

        check_branch(
            3'b101,
            32'd20,
            32'd10,
            1'b1,
            "BGE - Greater Than"
        );

        check_branch(
            3'b101,
            32'd10,
            32'd20,
            1'b0,
            "BGE - Less Than"
        );

        //------------------------------------------------------
        // BLTU - Unsigned
        //------------------------------------------------------

        check_branch(
            3'b110,
            32'd10,
            32'd20,
            1'b1,
            "BLTU - Less Than"
        );

        check_branch(
            3'b110,
            32'd20,
            32'd10,
            1'b0,
            "BLTU - Greater Than"
        );

        //------------------------------------------------------
        // BGEU - Unsigned
        //------------------------------------------------------

        check_branch(
            3'b111,
            32'd20,
            32'd10,
            1'b1,
            "BGEU - Greater Than"
        );

        check_branch(
            3'b111,
            32'd10,
            32'd20,
            1'b0,
            "BGEU - Less Than"
        );

        //------------------------------------------------------
        // Invalid funct3
        //------------------------------------------------------

        check_branch(
            3'b010,
            32'd10,
            32'd10,
            1'b0,
            "Invalid funct3"
        );

        //------------------------------------------------------
        // Verification Summary
        //------------------------------------------------------

        $display("");
        $display("=================================================");
        $display("Verification Summary");
        $display("=================================================");

        $display("Tests  : %0d", tests);
        $display("Errors : %0d", errors);

        $display("");

        if (errors == 0) begin

            $display("***********************************************");
            $display("*                                             *");
            $display("*       ALL TESTS PASSED SUCCESSFULLY!       *");
            $display("*                                             *");
            $display("***********************************************");

        end

        else begin

            $display("***********************************************");
            $display("*                                             *");
            $display("*       VERIFICATION FAILED                   *");
            $display("*                                             *");
            $display("*       Errors : %0d                           *", errors);
            $display("*                                             *");
            $display("***********************************************");

        end

        $finish;

    end

endmodule

`default_nettype wire

sim/branch_unit/branch_unit.vcd
$date
	Sun Aug 09 09:31:41 2026
$end
$version
	Icarus Verilog
$end
$timescale
	1ps
$end
$scope module branch_unit_tb $end
$var wire 1 ! branch_taken $end
$var reg 3 " funct3 [2:0] $end
$var reg 32 # rs1_data [31:0] $end
$var reg 32 $ rs2_data [31:0] $end
$var integer 32 % errors [31:0] $end
$var integer 32 & tests [31:0] $end
$scope module DUT $end
$var wire 3 ' funct3 [2:0] $end
$var wire 32 ( rs1_data [31:0] $end
$var wire 32 ) rs2_data [31:0] $end
$var reg 1 ! branch_taken $end
$upscope $end
$scope task check_branch $end
$var reg 1 * expected $end
$var reg 3 + test_funct3 [2:0] $end
$var reg 128 , test_name [127:0] $end
$var reg 32 - test_rs1 [31:0] $end
$var reg 32 . test_rs2 [31:0] $end
$upscope $end
$upscope $end
$enddefinitions $end
#0
$dumpvars
bx .
bx -
bx ,
bx +
x*
b0 )
b0 (
b0 '
b0 &
b0 %
b0 $
b0 #
b0 "
1!
$end
#5000
1!
b1010 $
b1010 )
b1010 #
b1010 (
b100001001000101010100010010000000101101001000000100010101110001011101010110000101101100 ,
1*
b1010 .
b1010 -
b0 +
#6000
0!
b10100 $
b10100 )
b10000100100010101010001001000000010110100100000010011100110111101110100001000000100010101110001011101010110000101101100 ,
0*
b10100 .
b1 &
#7000
1!
b1 "
b1 '
b10000100100111001000101001000000010110100100000010011100110111101110100001000000100010101110001011101010110000101101100 ,
1*
b1 +
b10 &
#8000
0!
b1010 $
b1010 )
b100001001001110010001010010000000101101001000000100010101110001011101010110000101101100 ,
0*
b1010 .
b11 &
#9000
1!
b10100 $
b10100 )
b100 "
b100 '
b10000100100110001010100001000000010110100100000010011000110010101110011011100110010000001010100011010000110000101101110 ,
1*
b10100 .
b100 +
b100 &
#10000
0!
b1010 $
b1010 )
b10100 #
b10100 (
b1010100001000000010110100100000010001110111001001100101011000010111010001100101011100100010000001010100011010000110000101101110 ,
0*
b1010 .
b10100 -
b101 &
#11000
1!
b101 "
b101 '
b1000101001000000010110100100000010001110111001001100101011000010111010001100101011100100010000001010100011010000110000101101110 ,
1*
b101 +
b110 &
#12000
0!
b10100 $
b10100 )
b1010 #
b1010 (
b10000100100011101000101001000000010110100100000010011000110010101110011011100110010000001010100011010000110000101101110 ,
0*
b10100 .
b1010 -
b111 &
#13000
1!
b110 "
b110 '
b1000010010011000101010001010101001000000010110100100000010011000110010101110011011100110010000001010100011010000110000101101110 ,
1*
b110 +
b1000 &
#14000
0!
b1010 $
b1010 )
b10100 #
b10100 (
b1010101001000000010110100100000010001110111001001100101011000010111010001100101011100100010000001010100011010000110000101101110 ,
0*
b1010 .
b10100 -
b1001 &
#15000
1!
b111 "
b111 '
1*
b111 +
b1010 &
#16000
0!
b10100 $
b10100 )
b1010 #
b1010 (
b1000010010001110100010101010101001000000010110100100000010011000110010101110011011100110010000001010100011010000110000101101110 ,
0*
b10100 .
b1010 -
b1011 &
#17000
b1010 $
b1010 )
b10 "
b10 '
b100100101101110011101100110000101101100011010010110010000100000011001100111010101101110011000110111010000110011 ,
b1010 .
b10 +
b1100 &
#18000
b1101 &
