rtl/common/rv32i_defs.vh
`ifndef RV32I_DEFS_VH
`define RV32I_DEFS_VH

//--------------------------------------------------------------
// RV32I ALU Operation Codes
//--------------------------------------------------------------

`define ALU_ADD    4'b0000
`define ALU_SUB    4'b0001
`define ALU_AND    4'b0010
`define ALU_OR     4'b0011
`define ALU_XOR    4'b0100
`define ALU_SLL    4'b0101
`define ALU_SRL    4'b0110
`define ALU_SRA    4'b0111
`define ALU_SLT    4'b1000
`define ALU_SLTU   4'b1001
`define ALU_PASS_B 4'b1010

`define OPCODE_OP_IMM   7'b0010011
`define OPCODE_LOAD     7'b0000011
`define OPCODE_STORE    7'b0100011
`define OPCODE_BRANCH   7'b1100011
`define OPCODE_LUI      7'b0110111
`define OPCODE_AUIPC    7'b0010111
`define OPCODE_JAL      7'b1101111
`define OPCODE_JALR     7'b1100111

`endif

rtl/common/rv32i_params.vh
`ifndef RV32I_PARAMS_VH
`define RV32I_PARAMS_VH

//==============================================================
// File        : rv32i_params.vh
// Description :
//   Global architectural parameters for the RV32I processor.
//
//   This file contains processor-wide constants that are shared
//   across multiple RTL modules.
//
//==============================================================

///////////////////////////////////////////////////////////////
// Processor Configuration
///////////////////////////////////////////////////////////////

`define XLEN                32
`define REG_COUNT           32
`define REG_ADDR_WIDTH      5

///////////////////////////////////////////////////////////////
// Program Counter
///////////////////////////////////////////////////////////////

`define RESET_VECTOR        32'h00000000
`define INSTRUCTION_SIZE    32'd4

///////////////////////////////////////////////////////////////
// Instruction Memory
///////////////////////////////////////////////////////////////

`define IMEM_DEPTH          1024

///////////////////////////////////////////////////////////////
// Data Memory
///////////////////////////////////////////////////////////////

`define DMEM_DEPTH          1024

///////////////////////////////////////////////////////////////
// SHA-256 Accelerator
///////////////////////////////////////////////////////////////

`define SHA_BLOCK_WIDTH     512
`define SHA_HASH_WIDTH      256

///////////////////////////////////////////////////////////////
// General Constants
///////////////////////////////////////////////////////////////

`define TRUE               1'b1
`define FALSE              1'b0

`endif

rtl/core/immediate_generator.v
`default_nettype none

`include "rv32i_params.vh"
`include "rv32i_defs.vh"

//==============================================================
// Module      : immediate_generator
// Description :
//   Generates the 32-bit immediate value from an RV32I
//   instruction.
//
// Supported Formats:
//   - I-Type
//   - S-Type
//   - B-Type
//   - U-Type
//   - J-Type
//
// Features:
//   - Pure combinational implementation
//   - Automatic sign extension
//   - Parameterized data width
//
// Target FPGA : Xilinx Artix-7 (Basys-3)
//==============================================================

module immediate_generator #(
    parameter DATA_WIDTH = `XLEN
)(
    //----------------------------------------------------------
    // Instruction Input
    //----------------------------------------------------------
    input  wire [DATA_WIDTH-1:0] instruction,

    //----------------------------------------------------------
    // Immediate Output
    //----------------------------------------------------------
    output reg  [DATA_WIDTH-1:0] immediate
);

    //----------------------------------------------------------
    // Internal Signals
    //----------------------------------------------------------

    wire [6:0] opcode;

    assign opcode = instruction[6:0];

    //----------------------------------------------------------
    // Immediate Generation
    //----------------------------------------------------------

    always @(*) begin

        case (opcode)

            //--------------------------------------------------
            // I-Type
            // ADDI, SLTI, XORI, ORI, ANDI
            // Loads
            // JALR
            //--------------------------------------------------

            `OPCODE_OP_IMM,
            `OPCODE_LOAD,
            `OPCODE_JALR :

                immediate = {
                    {20{instruction[31]}},
                    instruction[31:20]
                };

            //--------------------------------------------------
            // S-Type
            // Store Instructions
            //--------------------------------------------------

            `OPCODE_STORE :

                immediate = {
                    {20{instruction[31]}},
                    instruction[31:25],
                    instruction[11:7]
                };

            //--------------------------------------------------
            // B-Type
            // Branch Instructions
            //--------------------------------------------------

            `OPCODE_BRANCH :

                immediate = {
                    {19{instruction[31]}},
                    instruction[31],
                    instruction[7],
                    instruction[30:25],
                    instruction[11:8],
                    1'b0
                };

            //--------------------------------------------------
            // U-Type
            // LUI / AUIPC
            //--------------------------------------------------

            `OPCODE_LUI,
            `OPCODE_AUIPC :

                immediate = {
                    instruction[31:12],
                    12'b0
                };

            //--------------------------------------------------
            // J-Type
            // JAL
            //--------------------------------------------------

            `OPCODE_JAL :

                immediate = {
                    {11{instruction[31]}},
                    instruction[31],
                    instruction[19:12],
                    instruction[20],
                    instruction[30:21],
                    1'b0
                };

            //--------------------------------------------------
            // Default
            //--------------------------------------------------

            default :

                immediate = {DATA_WIDTH{1'b0}};

        endcase

    end

endmodule

`default_nettype wire

tb/core/immediate_generator_tb.v
`timescale 1ns/1ps
`default_nettype none

`include "rv32i_params.vh"
`include "rv32i_defs.vh"

//==============================================================
// Module      : immediate_generator_tb
// Description :
//   Self-checking testbench for the RV32I Immediate Generator.
//
//==============================================================

module immediate_generator_tb;

    //----------------------------------------------------------
    // Parameters
    //----------------------------------------------------------

    parameter DATA_WIDTH = `XLEN;

    //----------------------------------------------------------
    // DUT Signals
    //----------------------------------------------------------

    reg  [DATA_WIDTH-1:0] instruction;

    wire [DATA_WIDTH-1:0] immediate;

    //----------------------------------------------------------
    // Verification Statistics
    //----------------------------------------------------------

    integer tests;
    integer errors;

    //----------------------------------------------------------
    // DUT
    //----------------------------------------------------------

    immediate_generator DUT (

        .instruction(instruction),
        .immediate(immediate)

    );

    //----------------------------------------------------------
    // Waveform Dump
    //----------------------------------------------------------

    initial begin

        $dumpfile("sim/immediate_generator/immediate_generator.vcd");
        $dumpvars(0, immediate_generator_tb);

    end

    //----------------------------------------------------------
    // TASK : Check Immediate
    //----------------------------------------------------------

    task check_immediate;

        input [31:0] instr;
        input [31:0] expected;
        input [127:0] test_name;

    begin

        instruction = instr;

        #1;

        tests = tests + 1;

        if(immediate !== expected) begin

            $display("[FAIL] %s", test_name);
            $display("       Expected = %h", expected);
            $display("       Got      = %h", immediate);

            errors = errors + 1;

        end

        else begin

            $display("[PASS] %s -> %h",
                     test_name,
                     immediate);

        end

    end

    endtask

    //----------------------------------------------------------
    // Test Sequence
    //----------------------------------------------------------

    initial begin

        instruction = 32'd0;

        tests  = 0;
        errors = 0;

        #5;

        $display("");
        $display("=================================================");
        $display(" Immediate Generator Verification");
        $display("=================================================");

        //------------------------------------------------------
        // I-Type
        //------------------------------------------------------

        check_immediate(
            32'h00500093,
            32'h00000005,
            "I-Type ADDI +5"
        );

        //------------------------------------------------------
        // I-Type Negative
        //------------------------------------------------------

        check_immediate(
            32'hFFF00093,
            32'hFFFFFFFF,
            "I-Type ADDI -1"
        );

        //------------------------------------------------------
        // S-Type
        //------------------------------------------------------
        // sw x5,8(x1)
        //------------------------------------------------------

        check_immediate(
            32'h0050A423,
            32'h00000008,
            "S-Type Store"
        );

        //------------------------------------------------------
        // B-Type
        //------------------------------------------------------
        // Branch offset = 16
        //------------------------------------------------------

        check_immediate(
            32'h00208863,
            32'h00000010,
            "B-Type Branch"
        );

        //------------------------------------------------------
        // U-Type
        //------------------------------------------------------

        check_immediate(
            32'h123450B7,
            32'h12345000,
            "U-Type LUI"
        );

        //------------------------------------------------------
        // J-Type
        //------------------------------------------------------
        // Jump offset = 32
        //------------------------------------------------------

        check_immediate(
            32'h020000EF,
            32'h00000020,
            "J-Type JAL"
        );

        //------------------------------------------------------
        // Invalid Opcode
        //------------------------------------------------------

        check_immediate(
            32'h00000000,
            32'h00000000,
            "Default Case"
        );

        //------------------------------------------------------
        // Summary
        //------------------------------------------------------

        $display("");
        $display("=================================================");
        $display("Verification Summary");
        $display("=================================================");

        $display("Tests  : %0d", tests);
        $display("Errors : %0d", errors);

        if(errors == 0) begin

            $display("");
            $display("***********************************************");
            $display("*                                             *");
            $display("*       ALL TESTS PASSED SUCCESSFULLY!        *");
            $display("*                                             *");
            $display("***********************************************");

        end

        else begin

            $display("");
            $display("***********************************************");
            $display("*                                             *");
            $display("*      VERIFICATION FAILED                    *");
            $display("*                                             *");
            $display("*      Errors : %0d                           *", errors);
            $display("*                                             *");
            $display("***********************************************");

        end

        $finish;

    end

endmodule

`default_nettype wire

sim/immediate_generator/immediate_generator.vcd
$date
	Sat Aug 08 13:52:14 2026
$end
$version
	Icarus Verilog
$end
$timescale
	1ps
$end
$scope module immediate_generator_tb $end
$var wire 32 ! immediate [31:0] $end
$var reg 32 " instruction [31:0] $end
$var integer 32 # errors [31:0] $end
$var integer 32 $ tests [31:0] $end
$scope module DUT $end
$var wire 32 % instruction [31:0] $end
$var wire 7 & opcode [6:0] $end
$var reg 32 ' immediate [31:0] $end
$upscope $end
$scope task check_immediate $end
$var reg 32 ( expected [31:0] $end
$var reg 32 ) instr [31:0] $end
$var reg 128 * test_name [127:0] $end
$upscope $end
$upscope $end
$enddefinitions $end
#0
$dumpvars
bx *
bx )
bx (
b0 '
b0 &
b0 %
b0 $
b0 #
b0 "
b0 !
$end
#5000
b101 !
b101 '
b10011 &
b10100000000000010010011 "
b10100000000000010010011 %
b100100100101101010101000111100101110000011001010010000001000001010001000100010001001001001000000010101100110101 *
b101 (
b10100000000000010010011 )
#6000
b11111111111111111111111111111111 !
b11111111111111111111111111111111 '
b11111111111100000000000010010011 "
b11111111111100000000000010010011 %
b100100100101101010101000111100101110000011001010010000001000001010001000100010001001001001000000010110100110001 *
b11111111111111111111111111111111 (
b11111111111100000000000010010011 )
b1 $
#7000
b1000 !
b1000 '
b100011 &
b10100001010010000100011 "
b10100001010010000100011 %
b10100110010110101010100011110010111000001100101001000000101001101110100011011110111001001100101 *
b1000 (
b10100001010010000100011 )
b10 $
#8000
b10000 !
b10000 '
b1100011 &
b1000001000100001100011 "
b1000001000100001100011 %
b1000010001011010101010001111001011100000110010100100000010000100111001001100001011011100110001101101000 *
b10000 (
b1000001000100001100011 )
b11 $
#9000
b10010001101000101000000000000 !
b10010001101000101000000000000 '
b110111 &
b10010001101000101000010110111 "
b10010001101000101000010110111 %
b1010101001011010101010001111001011100000110010100100000010011000101010101001001 *
b10010001101000101000000000000 (
b10010001101000101000010110111 )
b100 $
#10000
b100000 !
b100000 '
b1101111 &
b10000000000000000011101111 "
b10000000000000000011101111 %
b1001010001011010101010001111001011100000110010100100000010010100100000101001100 *
b100000 (
b10000000000000000011101111 )
b101 $
#11000
b0 !
b0 '
b0 &
b0 "
b0 %
b10001000110010101100110011000010111010101101100011101000010000001000011011000010111001101100101 *
b0 (
b0 )
b110 $
#12000
b111 $
