rtl/common/rv32i_defs.vh
`ifndef RV32I_DEFS_VH
`define RV32I_DEFS_VH

//--------------------------------------------------------------
// RV32I ALU Operation Codes
//--------------------------------------------------------------

`define ALU_ADD    4'b0000
`define ALU_SUB    4'b0001
`define ALU_AND    4'b0010
`define ALU_OR     4'b0011
`define ALU_XOR    4'b0100
`define ALU_SLL    4'b0101
`define ALU_SRL    4'b0110
`define ALU_SRA    4'b0111
`define ALU_SLT    4'b1000
`define ALU_SLTU   4'b1001
`define ALU_PASS_B 4'b1010

`define OPCODE_OP_IMM   7'b0010011
`define OPCODE_LOAD     7'b0000011
`define OPCODE_STORE    7'b0100011
`define OPCODE_BRANCH   7'b1100011
`define OPCODE_LUI      7'b0110111
`define OPCODE_AUIPC    7'b0010111
`define OPCODE_JAL      7'b1101111
`define OPCODE_JALR     7'b1100111

`endif

rtl/common/rv32i_params.vh
`ifndef RV32I_PARAMS_VH
`define RV32I_PARAMS_VH

//==============================================================
// File        : rv32i_params.vh
// Description :
//   Global architectural parameters for the RV32I processor.
//
//   This file contains processor-wide constants that are shared
//   across multiple RTL modules.
//
//==============================================================

///////////////////////////////////////////////////////////////
// Processor Configuration
///////////////////////////////////////////////////////////////

`define XLEN                32
`define REG_COUNT           32
`define REG_ADDR_WIDTH      5

///////////////////////////////////////////////////////////////
// Program Counter
///////////////////////////////////////////////////////////////

`define RESET_VECTOR        32'h00000000
`define INSTRUCTION_SIZE    32'd4

///////////////////////////////////////////////////////////////
// Instruction Memory
///////////////////////////////////////////////////////////////

`define IMEM_DEPTH          1024

///////////////////////////////////////////////////////////////
// Data Memory
///////////////////////////////////////////////////////////////

`define DMEM_DEPTH          1024

///////////////////////////////////////////////////////////////
// SHA-256 Accelerator
///////////////////////////////////////////////////////////////

`define SHA_BLOCK_WIDTH     512
`define SHA_HASH_WIDTH      256

///////////////////////////////////////////////////////////////
// General Constants
///////////////////////////////////////////////////////////////

`define TRUE               1'b1
`define FALSE              1'b0

`endif

rtl/core/alu_control.v
`default_nettype none

`include "rv32i_params.vh"
`include "rv32i_defs.vh"

//==============================================================
// Module      : alu_control
// Description :
//   ALU Control Unit for the RV32I processor.
//
//   Converts the high-level ALU operation class generated by
//   the Main Control Unit and the instruction's funct3/funct7
//   fields into the 4-bit operation code understood by the ALU.
//
// Inputs:
//   - ALUOp  : Operation class from Main Control Unit
//   - funct3 : Instruction funct3 field
//   - funct7 : Instruction funct7 field
//
// Output:
//   - alu_control : Operation code for the ALU
//
// ALUOp:
//   00 -> Address calculation / ADD
//   01 -> Branch comparison / SUB
//   10 -> R-Type / I-Type ALU operation
//
// Target FPGA : Xilinx Artix-7 (Basys-3)
//==============================================================

module alu_control (
    //----------------------------------------------------------
    // Control Inputs
    //----------------------------------------------------------

    input wire [1:0] ALUOp,

    //----------------------------------------------------------
    // Instruction Fields
    //----------------------------------------------------------

    input wire [2:0] funct3,
    input wire [6:0] funct7,

    //----------------------------------------------------------
    // ALU Operation Output
    //----------------------------------------------------------

    output reg [3:0] alu_control
);

    //----------------------------------------------------------
    // ALU Control Logic
    //----------------------------------------------------------

    always @(*) begin

        //------------------------------------------------------
        // Safe Default
        //------------------------------------------------------

        alu_control = `ALU_ADD;

        //------------------------------------------------------
        // Decode ALU Operation Class
        //------------------------------------------------------

        case (ALUOp)

            //--------------------------------------------------
            // Address Calculation
            //
            // Used by:
            //   Load
            //   Store
            //   JALR
            //
            // Operation:
            //   Base Register + Immediate
            //--------------------------------------------------

            2'b00: begin

                alu_control = `ALU_ADD;

            end

            //--------------------------------------------------
            // Branch Comparison
            //
            // Initial implementation uses subtraction so that
            // the ALU zero flag can be used for equality.
            //--------------------------------------------------

            2'b01: begin

                alu_control = `ALU_SUB;

            end

            //--------------------------------------------------
            // R-Type / I-Type ALU Operations
            //--------------------------------------------------

            2'b10: begin

                case (funct3)

                    //--------------------------------------------------
                    // ADD / ADDI
                    // SUB
                    //--------------------------------------------------

                    3'b000: begin

                        if (funct7 == 7'b0100000)
                            alu_control = `ALU_SUB;
                        else
                            alu_control = `ALU_ADD;

                    end

                    //--------------------------------------------------
                    // SLL / SLLI
                    //--------------------------------------------------

                    3'b001: begin

                        alu_control = `ALU_SLL;

                    end

                    //--------------------------------------------------
                    // SLT / SLTI
                    //--------------------------------------------------

                    3'b010: begin

                        alu_control = `ALU_SLT;

                    end

                    //--------------------------------------------------
                    // SLTU / SLTIU
                    //--------------------------------------------------

                    3'b011: begin

                        alu_control = `ALU_SLTU;

                    end

                    //--------------------------------------------------
                    // XOR / XORI
                    //--------------------------------------------------

                    3'b100: begin

                        alu_control = `ALU_XOR;

                    end

                    //--------------------------------------------------
                    // SRL / SRA
                    // SRLI / SRAI
                    //--------------------------------------------------

                    3'b101: begin

                        if (funct7 == 7'b0100000)
                            alu_control = `ALU_SRA;
                        else
                            alu_control = `ALU_SRL;

                    end

                    //--------------------------------------------------
                    // OR / ORI
                    //--------------------------------------------------

                    3'b110: begin

                        alu_control = `ALU_OR;

                    end

                    //--------------------------------------------------
                    // AND / ANDI
                    //--------------------------------------------------

                    3'b111: begin

                        alu_control = `ALU_AND;

                    end

                    //--------------------------------------------------
                    // Unsupported funct3
                    //--------------------------------------------------

                    default: begin

                        alu_control = `ALU_ADD;

                    end

                endcase

            end

            //--------------------------------------------------
            // Unsupported ALUOp
            //--------------------------------------------------

            default: begin

                alu_control = `ALU_ADD;

            end

        endcase

    end

endmodule

`default_nettype wire

tb/core/alu_control_tb.v
`timescale 1ns/1ps
`default_nettype none

`include "rv32i_params.vh"
`include "rv32i_defs.vh"

//==============================================================
// Module      : alu_control_tb
// Description :
//   Self-checking testbench for the RV32I ALU Control Unit.
//
//   Tests:
//   - Address calculation
//   - Branch comparison
//   - R-Type ALU operations
//   - I-Type ALU operations
//   - ADD/SUB distinction
//   - SRL/SRA distinction
//   - Invalid ALUOp
//
//==============================================================

module alu_control_tb;

    //----------------------------------------------------------
    // DUT Inputs
    //----------------------------------------------------------

    reg [1:0] ALUOp;
    reg [2:0] funct3;
    reg [6:0] funct7;

    //----------------------------------------------------------
    // DUT Output
    //----------------------------------------------------------

    wire [3:0] alu_control;

    //----------------------------------------------------------
    // Verification Statistics
    //----------------------------------------------------------

    integer tests;
    integer errors;

    //----------------------------------------------------------
    // Device Under Test
    //----------------------------------------------------------

    alu_control DUT (
        .ALUOp       (ALUOp),
        .funct3      (funct3),
        .funct7      (funct7),
        .alu_control (alu_control)
    );

    //----------------------------------------------------------
    // Waveform Dump
    //----------------------------------------------------------

    initial begin

        $dumpfile("sim/alu_control/alu_control.vcd");
        $dumpvars(0, alu_control_tb);

    end

    //----------------------------------------------------------
    // TASK : Check ALU Control
    //----------------------------------------------------------

    task check_alu_control;

        input [1:0]   test_ALUOp;
        input [2:0]   test_funct3;
        input [6:0]   test_funct7;
        input [3:0]   expected;
        input [127:0] test_name;

    begin

        //------------------------------------------------------
        // Apply Inputs
        //------------------------------------------------------

        ALUOp  = test_ALUOp;
        funct3 = test_funct3;
        funct7 = test_funct7;

        #1;

        tests = tests + 1;

        //------------------------------------------------------
        // Compare Output
        //------------------------------------------------------

        if (alu_control !== expected) begin

            $display("");
            $display("[FAIL] %s", test_name);

            $display("       Inputs:");
            $display("       ALUOp  = %b", test_ALUOp);
            $display("       funct3 = %b", test_funct3);
            $display("       funct7 = %b", test_funct7);

            $display("       Expected = %b", expected);
            $display("       Got      = %b", alu_control);

            errors = errors + 1;

        end

        else begin

            $display("[PASS] %s -> %b",
                     test_name,
                     alu_control);

        end

    end

    endtask

    //----------------------------------------------------------
    // Test Sequence
    //----------------------------------------------------------

    initial begin

        ALUOp  = 2'b00;
        funct3 = 3'b000;
        funct7 = 7'b0000000;

        tests  = 0;
        errors = 0;

        #5;

        $display("");
        $display("=================================================");
        $display("          ALU Control Unit Verification");
        $display("=================================================");

        //------------------------------------------------------
        // ALUOp = 00
        // Address Calculation
        //------------------------------------------------------

        check_alu_control(
            2'b00,
            3'b000,
            7'b0000000,
            `ALU_ADD,
            "Address Calculation -> ADD"
        );

        //------------------------------------------------------
        // ALUOp = 01
        // Branch Comparison
        //------------------------------------------------------

        check_alu_control(
            2'b01,
            3'b000,
            7'b0000000,
            `ALU_SUB,
            "Branch Comparison -> SUB"
        );

        //------------------------------------------------------
        // R-Type ADD
        //------------------------------------------------------

        check_alu_control(
            2'b10,
            3'b000,
            7'b0000000,
            `ALU_ADD,
            "R-Type ADD"
        );

        //------------------------------------------------------
        // R-Type SUB
        //------------------------------------------------------

        check_alu_control(
            2'b10,
            3'b000,
            7'b0100000,
            `ALU_SUB,
            "R-Type SUB"
        );

        //------------------------------------------------------
        // R-Type SLL
        //------------------------------------------------------

        check_alu_control(
            2'b10,
            3'b001,
            7'b0000000,
            `ALU_SLL,
            "R-Type SLL"
        );

        //------------------------------------------------------
        // R-Type SLT
        //------------------------------------------------------

        check_alu_control(
            2'b10,
            3'b010,
            7'b0000000,
            `ALU_SLT,
            "R-Type SLT"
        );

        //------------------------------------------------------
        // R-Type SLTU
        //------------------------------------------------------

        check_alu_control(
            2'b10,
            3'b011,
            7'b0000000,
            `ALU_SLTU,
            "R-Type SLTU"
        );

        //------------------------------------------------------
        // R-Type XOR
        //------------------------------------------------------

        check_alu_control(
            2'b10,
            3'b100,
            7'b0000000,
            `ALU_XOR,
            "R-Type XOR"
        );

        //------------------------------------------------------
        // R-Type SRL
        //------------------------------------------------------

        check_alu_control(
            2'b10,
            3'b101,
            7'b0000000,
            `ALU_SRL,
            "R-Type SRL"
        );

        //------------------------------------------------------
        // R-Type SRA
        //------------------------------------------------------

        check_alu_control(
            2'b10,
            3'b101,
            7'b0100000,
            `ALU_SRA,
            "R-Type SRA"
        );

        //------------------------------------------------------
        // R-Type OR
        //------------------------------------------------------

        check_alu_control(
            2'b10,
            3'b110,
            7'b0000000,
            `ALU_OR,
            "R-Type OR"
        );

        //------------------------------------------------------
        // R-Type AND
        //------------------------------------------------------

        check_alu_control(
            2'b10,
            3'b111,
            7'b0000000,
            `ALU_AND,
            "R-Type AND"
        );

        //------------------------------------------------------
        // I-Type ADDI
        //------------------------------------------------------

        check_alu_control(
            2'b10,
            3'b000,
            7'b0000000,
            `ALU_ADD,
            "I-Type ADDI -> ADD"
        );

        //------------------------------------------------------
        // I-Type SLTI
        //------------------------------------------------------

        check_alu_control(
            2'b10,
            3'b010,
            7'b0000000,
            `ALU_SLT,
            "I-Type SLTI -> SLT"
        );

        //------------------------------------------------------
        // I-Type SLTIU
        //------------------------------------------------------

        check_alu_control(
            2'b10,
            3'b011,
            7'b0000000,
            `ALU_SLTU,
            "I-Type SLTIU -> SLTU"
        );

        //------------------------------------------------------
        // I-Type XORI
        //------------------------------------------------------

        check_alu_control(
            2'b10,
            3'b100,
            7'b0000000,
            `ALU_XOR,
            "I-Type XORI -> XOR"
        );

        //------------------------------------------------------
        // I-Type ORI
        //------------------------------------------------------

        check_alu_control(
            2'b10,
            3'b110,
            7'b0000000,
            `ALU_OR,
            "I-Type ORI -> OR"
        );

        //------------------------------------------------------
        // I-Type ANDI
        //------------------------------------------------------

        check_alu_control(
            2'b10,
            3'b111,
            7'b0000000,
            `ALU_AND,
            "I-Type ANDI -> AND"
        );

        //------------------------------------------------------
        // I-Type SLLI
        //------------------------------------------------------

        check_alu_control(
            2'b10,
            3'b001,
            7'b0000000,
            `ALU_SLL,
            "I-Type SLLI -> SLL"
        );

        //------------------------------------------------------
        // I-Type SRLI
        //------------------------------------------------------

        check_alu_control(
            2'b10,
            3'b101,
            7'b0000000,
            `ALU_SRL,
            "I-Type SRLI -> SRL"
        );

        //------------------------------------------------------
        // I-Type SRAI
        //------------------------------------------------------

        check_alu_control(
            2'b10,
            3'b101,
            7'b0100000,
            `ALU_SRA,
            "I-Type SRAI -> SRA"
        );

        //------------------------------------------------------
        // Invalid ALUOp
        //------------------------------------------------------

        check_alu_control(
            2'b11,
            3'b111,
            7'b1111111,
            `ALU_ADD,
            "Invalid ALUOp"
        );

        //------------------------------------------------------
        // Verification Summary
        //------------------------------------------------------

        $display("");
        $display("=================================================");
        $display("Verification Summary");
        $display("=================================================");

        $display("Tests  : %0d", tests);
        $display("Errors : %0d", errors);

        $display("");

        if (errors == 0) begin

            $display("***********************************************");
            $display("*                                             *");
            $display("*       ALL TESTS PASSED SUCCESSFULLY!       *");
            $display("*                                             *");
            $display("***********************************************");

        end

        else begin

            $display("***********************************************");
            $display("*                                             *");
            $display("*       VERIFICATION FAILED                   *");
            $display("*                                             *");
            $display("*       Errors : %0d                           *", errors);
            $display("*                                             *");
            $display("***********************************************");

        end

        $finish;

    end

endmodule

`default_nettype wire

sim/alu_control/alu_control.vcd
$date
	Sun Aug 09 09:17:42 2026
$end
$version
	Icarus Verilog
$end
$timescale
	1ps
$end
$scope module alu_control_tb $end
$var wire 4 ! alu_control [3:0] $end
$var reg 2 " ALUOp [1:0] $end
$var reg 3 # funct3 [2:0] $end
$var reg 7 $ funct7 [6:0] $end
$var integer 32 % errors [31:0] $end
$var integer 32 & tests [31:0] $end
$scope module DUT $end
$var wire 2 ' ALUOp [1:0] $end
$var wire 3 ( funct3 [2:0] $end
$var wire 7 ) funct7 [6:0] $end
$var reg 4 * alu_control [3:0] $end
$upscope $end
$scope task check_alu_control $end
$var reg 4 + expected [3:0] $end
$var reg 2 , test_ALUOp [1:0] $end
$var reg 3 - test_funct3 [2:0] $end
$var reg 7 . test_funct7 [6:0] $end
$var reg 128 / test_name [127:0] $end
$upscope $end
$upscope $end
$enddefinitions $end
#0
$dumpvars
bx /
bx .
bx -
bx ,
bx +
b0 *
b0 )
b0 (
b0 '
b0 &
b0 %
b0 $
b0 #
b0 "
b0 !
$end
#5000
b1101100011000110111010101101100011000010111010001101001011011110110111000100000001011010011111000100000010000010100010001000100 /
b0 +
b0 .
b0 -
b0 ,
#6000
b1 !
b1 *
b1 "
b1 '
b1101111011011010111000001100001011100100110100101110011011011110110111000100000001011010011111000100000010100110101010101000010 /
b1 +
b1 ,
b1 &
#7000
b0 !
b0 *
b10 "
b10 '
b1010010001011010101010001111001011100000110010100100000010000010100010001000100 /
b0 +
b10 ,
b10 &
#8000
b1 !
b1 *
b100000 $
b100000 )
b1010010001011010101010001111001011100000110010100100000010100110101010101000010 /
b1 +
b100000 .
b11 &
#9000
b101 !
b101 *
b0 $
b0 )
b1 #
b1 (
b1010010001011010101010001111001011100000110010100100000010100110100110001001100 /
b101 +
b0 .
b1 -
b100 &
#10000
b1000 !
b1000 *
b10 #
b10 (
b1010010001011010101010001111001011100000110010100100000010100110100110001010100 /
b1000 +
b10 -
b101 &
#11000
b1001 !
b1001 *
b11 #
b11 (
b101001000101101010101000111100101110000011001010010000001010011010011000101010001010101 /
b1001 +
b11 -
b110 &
#12000
b100 !
b100 *
b100 #
b100 (
b1010010001011010101010001111001011100000110010100100000010110000100111101010010 /
b100 +
b100 -
b111 &
#13000
b110 !
b110 *
b101 #
b101 (
b1010010001011010101010001111001011100000110010100100000010100110101001001001100 /
b110 +
b101 -
b1000 &
#14000
b111 !
b111 *
b100000 $
b100000 )
b1010010001011010101010001111001011100000110010100100000010100110101001001000001 /
b111 +
b100000 .
b1001 &
#15000
b11 !
b11 *
b0 $
b0 )
b110 #
b110 (
b10100100010110101010100011110010111000001100101001000000100111101010010 /
b11 +
b0 .
b110 -
b1010 &
#16000
b10 !
b10 *
b111 #
b111 (
b1010010001011010101010001111001011100000110010100100000010000010100111001000100 /
b10 +
b111 -
b1011 &
#17000
b0 !
b0 *
b0 #
b0 (
b1010100011110010111000001100101001000000100000101000100010001000100100100100000001011010011111000100000010000010100010001000100 /
b0 +
b0 -
b1100 &
#18000
b1000 !
b1000 *
b10 #
b10 (
b1010100011110010111000001100101001000000101001101001100010101000100100100100000001011010011111000100000010100110100110001010100 /
b1000 +
b10 -
b1101 &
#19000
b1001 !
b1001 *
b11 #
b11 (
b1110000011001010010000001010011010011000101010001001001010101010010000000101101001111100010000001010011010011000101010001010101 /
b1001 +
b11 -
b1110 &
#20000
b100 !
b100 *
b100 #
b100 (
b1010100011110010111000001100101001000000101100001001111010100100100100100100000001011010011111000100000010110000100111101010010 /
b100 +
b100 -
b1111 &
#21000
b11 !
b11 *
b110 #
b110 (
b1001001001011010101010001111001011100000110010100100000010011110101001001001001001000000010110100111110001000000100111101010010 /
b11 +
b110 -
b10000 &
#22000
b10 !
b10 *
b111 #
b111 (
b1010100011110010111000001100101001000000100000101001110010001000100100100100000001011010011111000100000010000010100111001000100 /
b10 +
b111 -
b10001 &
#23000
b101 !
b101 *
b1 #
b1 (
b1010100011110010111000001100101001000000101001101001100010011000100100100100000001011010011111000100000010100110100110001001100 /
b101 +
b1 -
b10010 &
#24000
b110 !
b110 *
b101 #
b101 (
b1010100011110010111000001100101001000000101001101010010010011000100100100100000001011010011111000100000010100110101001001001100 /
b110 +
b101 -
b10011 &
#25000
b111 !
b111 *
b100000 $
b100000 )
b1010100011110010111000001100101001000000101001101010010010000010100100100100000001011010011111000100000010100110101001001000001 /
b111 +
b100000 .
b10100 &
#26000
b0 !
b0 *
b1111111 $
b1111111 )
b111 #
b111 (
b11 "
b11 '
b1001001011011100111011001100001011011000110100101100100001000000100000101001100010101010100111101110000 /
b0 +
b1111111 .
b111 -
b11 ,
b10101 &
#27000
b10110 &
