rtl/common/register_file.v
`default_nettype none

//==============================================================
// Module      : register_file
// Project     : FPGA RISC-V SoC with SHA-256 Accelerator
// Description :
//   32 × 32-bit Register File for the RV32I processor.
//
// Features:
//   - Two asynchronous read ports
//   - One synchronous write port
//   - Register x0 is hardwired to zero
//   - Parameterized implementation
//
//==============================================================

module register_file #(
    parameter DATA_WIDTH = 32,
    parameter REG_COUNT  = 32,
    parameter ADDR_WIDTH = 5
)(
    input  wire                     clk,
    input  wire                     rst,

    input  wire                     reg_write,

    input  wire [ADDR_WIDTH-1:0]    rs1_addr,
    input  wire [ADDR_WIDTH-1:0]    rs2_addr,

    output wire [DATA_WIDTH-1:0]    rs1_data,
    output wire [DATA_WIDTH-1:0]    rs2_data,

    input  wire [ADDR_WIDTH-1:0]    rd_addr,
    input  wire [DATA_WIDTH-1:0]    rd_data
);

    //----------------------------------------------------------
    // Local Parameters
    //----------------------------------------------------------

    localparam [ADDR_WIDTH-1:0] ZERO_REG = {ADDR_WIDTH{1'b0}};

    //----------------------------------------------------------
    // Register Storage Array
    //----------------------------------------------------------

    reg [DATA_WIDTH-1:0] registers [0:REG_COUNT-1];

    integer i;

    //----------------------------------------------------------
    // Sequential Write Logic
    //----------------------------------------------------------

    always @(posedge clk) begin

        if (rst) begin

            for (i = 0; i < REG_COUNT; i = i + 1)
                registers[i] <= {DATA_WIDTH{1'b0}};

        end

        else if (reg_write && (rd_addr != ZERO_REG)) begin

            registers[rd_addr] <= rd_data;

        end

    end

    //----------------------------------------------------------
    // Asynchronous Read Port 1
    //----------------------------------------------------------

    assign rs1_data =
        (rs1_addr == ZERO_REG) ?
        {DATA_WIDTH{1'b0}} :
        registers[rs1_addr];

    //----------------------------------------------------------
    // Asynchronous Read Port 2
    //----------------------------------------------------------

    assign rs2_data =
        (rs2_addr == ZERO_REG) ?
        {DATA_WIDTH{1'b0}} :
        registers[rs2_addr];

endmodule

`default_nettype wire

tb/common/register_file_tb.v
`timescale 1ns/1ps
`default_nettype none

//==============================================================
// Module      : register_file_tb
// Project     : FPGA RISC-V SoC with SHA-256 Accelerator
// Description :
//   Self-checking testbench for the RV32I Register File.
//
// Features Tested:
//   - Reset
//   - x0 protection
//   - Single register writes
//   - Single register reads
//   - Dual read ports
//   - Highest register (x31)
//   - Write disable
//   - Consecutive writes
//
//==============================================================

module register_file_tb;

//--------------------------------------------------------------
// Parameters
//--------------------------------------------------------------

parameter DATA_WIDTH = 32;
parameter REG_COUNT  = 32;
parameter ADDR_WIDTH = 5;

//--------------------------------------------------------------
// DUT Signals
//--------------------------------------------------------------

reg clk;
reg rst;

reg reg_write;

reg [ADDR_WIDTH-1:0] rs1_addr;
reg [ADDR_WIDTH-1:0] rs2_addr;
reg [ADDR_WIDTH-1:0] rd_addr;

reg [DATA_WIDTH-1:0] rd_data;

wire [DATA_WIDTH-1:0] rs1_data;
wire [DATA_WIDTH-1:0] rs2_data;

//--------------------------------------------------------------
// Test Variables
//--------------------------------------------------------------

integer errors;

//--------------------------------------------------------------
// Device Under Test
//--------------------------------------------------------------

register_file DUT (

    .clk(clk),
    .rst(rst),

    .reg_write(reg_write),

    .rs1_addr(rs1_addr),
    .rs2_addr(rs2_addr),

    .rs1_data(rs1_data),
    .rs2_data(rs2_data),

    .rd_addr(rd_addr),
    .rd_data(rd_data)

);

//--------------------------------------------------------------
// Clock Generation (100 MHz)
//--------------------------------------------------------------

initial begin
    clk = 1'b0;
    forever #5 clk = ~clk;
end

//--------------------------------------------------------------
// Waveform Dump
//--------------------------------------------------------------

initial begin
    $dumpfile("register_file.vcd");
    $dumpvars(0, register_file_tb);
end

//--------------------------------------------------------------
// TASK : Reset DUT
//--------------------------------------------------------------

task reset_dut;
begin

    $display("\n=================================================");
    $display("[%0t] Resetting DUT...", $time);
    $display("=================================================\n");

    rst       = 1'b1;
    reg_write = 1'b0;

    rs1_addr  = 5'd0;
    rs2_addr  = 5'd0;

    rd_addr   = 5'd0;
    rd_data   = 32'd0;

    @(posedge clk);
    @(posedge clk);

    rst = 1'b0;

    @(posedge clk);

    $display("[%0t] Reset Complete\n",$time);

end
endtask

//--------------------------------------------------------------
// TASK : Write Register
//--------------------------------------------------------------

task write_reg;

    input [ADDR_WIDTH-1:0] addr;
    input [DATA_WIDTH-1:0] data;

begin

    $display("[%0t] WRITE : x%0d <= 0x%08h",
             $time, addr, data);

    rd_addr   = addr;
    rd_data   = data;
    reg_write = 1'b1;

    @(posedge clk);
    @(posedge clk);
    reg_write = 1'b0;

end

endtask

//--------------------------------------------------------------
// TASK : Check Register (Read Port 1)
//--------------------------------------------------------------

task check_reg;

    input [ADDR_WIDTH-1:0] addr;
    input [DATA_WIDTH-1:0] expected;

begin

    rs1_addr = addr;

    #1;

    if(rs1_data !== expected) begin

        $display("[FAIL] x%0d Expected = %h Got = %h",
                  addr,
                  expected,
                  rs1_data);

        errors = errors + 1;

    end

    else begin

        $display("[PASS] x%0d = %h",
                  addr,
                  rs1_data);

    end

end

endtask

//--------------------------------------------------------------
// TASK : Check Register (Read Port 2)
//--------------------------------------------------------------

task check_reg_rs2;

    input [ADDR_WIDTH-1:0] addr;
    input [DATA_WIDTH-1:0] expected;

begin

    rs2_addr = addr;

    #1;

    if(rs2_data !== expected) begin

        $display("[FAIL] x%0d Expected = %h Got = %h",
                  addr,
                  expected,
                  rs2_data);

        errors = errors + 1;

    end

    else begin

        $display("[PASS] x%0d = %h",
                  addr,
                  rs2_data);

    end

end

endtask

//--------------------------------------------------------------
// TASK : Dual Read Verification
//--------------------------------------------------------------

task check_dual_read;

    input [4:0] addr1;
    input [31:0] expected1;

    input [4:0] addr2;
    input [31:0] expected2;

begin

    rs1_addr = addr1;
    rs2_addr = addr2;

    #1;

    if(rs1_data !== expected1) begin

        $display("[FAIL] RS1");

        errors = errors + 1;

    end

    if(rs2_data !== expected2) begin

        $display("[FAIL] RS2");

        errors = errors + 1;

    end

    if((rs1_data === expected1) &&
       (rs2_data === expected2))

        $display("[PASS] Dual Read Successful");

end

endtask

//--------------------------------------------------------------
// Main Test Sequence
//--------------------------------------------------------------

initial begin

    errors = 0;

    //----------------------------------------------------------
    // Reset
    //----------------------------------------------------------

    reset_dut();

    //----------------------------------------------------------
    // Test x0
    //----------------------------------------------------------

    $display("\n---- Test : x0 Always Zero ----");

    check_reg(0,32'h00000000);

    //----------------------------------------------------------
    // Write x5
    //----------------------------------------------------------

    $display("\n---- Test : Write x5 ----");

    write_reg(5,32'hDEADBEEF);

    check_reg(5,32'hDEADBEEF);

    //----------------------------------------------------------
    // Attempt Write to x0
    //----------------------------------------------------------

    $display("\n---- Test : x0 Protection ----");

    write_reg(0,32'hFFFFFFFF);

    check_reg(0,32'h00000000);

    //----------------------------------------------------------
    // Highest Register
    //----------------------------------------------------------

    $display("\n---- Test : x31 ----");

    write_reg(31,32'h12345678);

    check_reg(31,32'h12345678);

    //----------------------------------------------------------
    // Consecutive Writes
    //----------------------------------------------------------

    $display("\n---- Test : Consecutive Writes ----");

    write_reg(10,32'hAAAAAAAA);

    write_reg(20,32'h55555555);

    check_reg(10,32'hAAAAAAAA);

    check_reg(20,32'h55555555);

    //----------------------------------------------------------
    // Read Port 2
    //----------------------------------------------------------

    $display("\n---- Test : Read Port 2 ----");

    check_reg_rs2(10,32'hAAAAAAAA);

    //----------------------------------------------------------
    // Dual Read
    //----------------------------------------------------------

    $display("\n---- Test : Dual Read ----");

    check_dual_read(

        10,
        32'hAAAAAAAA,

        20,
        32'h55555555

    );

    //----------------------------------------------------------
    // Write Disable
    //----------------------------------------------------------

    $display("\n---- Test : Write Disable ----");

    rd_addr = 8;
    rd_data = 32'hFFFFFFFF;

    reg_write = 1'b0;

    @(posedge clk);

    check_reg(8,32'h00000000);

    //----------------------------------------------------------
    // Simulation Summary
    //----------------------------------------------------------

    $display("\n==============================================");

    if(errors == 0)

        $display(" ALL TESTS PASSED ");

    else

        $display(" %0d TEST(S) FAILED ",errors);

    $display("==============================================");

    $finish;

end

endmodule

`default_nettype wire

sim/register_file/register_file.vcd
$date
	Thu Aug 06 19:40:20 2026
$end
$version
	Icarus Verilog
$end
$timescale
	1ps
$end
$scope module register_file_tb $end
$var wire 32 ! rs2_data [31:0] $end
$var wire 32 " rs1_data [31:0] $end
$var reg 1 # clk $end
$var reg 5 $ rd_addr [4:0] $end
$var reg 32 % rd_data [31:0] $end
$var reg 1 & reg_write $end
$var reg 5 ' rs1_addr [4:0] $end
$var reg 5 ( rs2_addr [4:0] $end
$var reg 1 ) rst $end
$var integer 32 * errors [31:0] $end
$scope module DUT $end
$var wire 1 # clk $end
$var wire 5 + rd_addr [4:0] $end
$var wire 32 , rd_data [31:0] $end
$var wire 1 & reg_write $end
$var wire 5 - rs1_addr [4:0] $end
$var wire 5 . rs2_addr [4:0] $end
$var wire 1 ) rst $end
$var wire 32 / rs2_data [31:0] $end
$var wire 32 0 rs1_data [31:0] $end
$var integer 32 1 i [31:0] $end
$upscope $end
$scope task check_dual_read $end
$var reg 5 2 addr1 [4:0] $end
$var reg 5 3 addr2 [4:0] $end
$var reg 32 4 expected1 [31:0] $end
$var reg 32 5 expected2 [31:0] $end
$upscope $end
$scope task check_reg $end
$var reg 5 6 addr [4:0] $end
$var reg 32 7 expected [31:0] $end
$upscope $end
$scope task check_reg_rs2 $end
$var reg 5 8 addr [4:0] $end
$var reg 32 9 expected [31:0] $end
$upscope $end
$scope task reset_dut $end
$upscope $end
$scope task write_reg $end
$var reg 5 : addr [4:0] $end
$var reg 32 ; data [31:0] $end
$upscope $end
$upscope $end
$enddefinitions $end
#0
$dumpvars
bx ;
bx :
bx 9
bx 8
bx 7
bx 6
bx 5
bx 4
bx 3
bx 2
bx 1
b0 0
b0 /
b0 .
b0 -
b0 ,
b0 +
b0 *
1)
b0 (
b0 '
0&
b0 %
b0 $
0#
b0 "
b0 !
$end
#5000
b100000 1
1#
#10000
0#
#15000
0)
b100000 1
1#
#20000
0#
#25000
b0 7
b0 6
1#
#26000
1&
b11011110101011011011111011101111 %
b11011110101011011011111011101111 ,
b101 $
b101 +
b11011110101011011011111011101111 ;
b101 :
#30000
0#
#35000
1#
#40000
0#
#45000
b11011110101011011011111011101111 "
b11011110101011011011111011101111 0
b101 '
b101 -
b11011110101011011011111011101111 7
b101 6
0&
1#
#46000
1&
b11111111111111111111111111111111 %
b11111111111111111111111111111111 ,
b0 $
b0 +
b11111111111111111111111111111111 ;
b0 :
#50000
0#
#55000
1#
#60000
0#
#65000
b0 "
b0 0
b0 '
b0 -
b0 7
b0 6
0&
1#
#66000
1&
b10010001101000101011001111000 %
b10010001101000101011001111000 ,
b11111 $
b11111 +
b10010001101000101011001111000 ;
b11111 :
#70000
0#
#75000
1#
#80000
0#
#85000
b10010001101000101011001111000 "
b10010001101000101011001111000 0
b11111 '
b11111 -
b10010001101000101011001111000 7
b11111 6
0&
1#
#86000
1&
b10101010101010101010101010101010 %
b10101010101010101010101010101010 ,
b1010 $
b1010 +
b10101010101010101010101010101010 ;
b1010 :
#90000
0#
#95000
1#
#100000
0#
#105000
b1010101010101010101010101010101 %
b1010101010101010101010101010101 ,
b10100 $
b10100 +
b1010101010101010101010101010101 ;
b10100 :
1&
1#
#110000
0#
#115000
1#
#120000
0#
#125000
b10101010101010101010101010101010 "
b10101010101010101010101010101010 0
b1010 '
b1010 -
b10101010101010101010101010101010 7
b1010 6
0&
1#
#126000
b1010101010101010101010101010101 "
b1010101010101010101010101010101 0
b10100 '
b10100 -
b1010101010101010101010101010101 7
b10100 6
#127000
b10101010101010101010101010101010 !
b10101010101010101010101010101010 /
b1010 (
b1010 .
b10101010101010101010101010101010 9
b1010 8
#128000
b1010101010101010101010101010101 !
b1010101010101010101010101010101 /
b10101010101010101010101010101010 "
b10101010101010101010101010101010 0
b10100 (
b10100 .
b1010 '
b1010 -
b1010101010101010101010101010101 5
b10100 3
b10101010101010101010101010101010 4
b1010 2
#129000
b11111111111111111111111111111111 %
b11111111111111111111111111111111 ,
b1000 $
b1000 +
#130000
0#
#135000
b0 "
b0 0
b1000 '
b1000 -
b0 7
b1000 6
1#
