rtl/common/rv32i_defs.vh
`ifndef RV32I_DEFS_VH
`define RV32I_DEFS_VH

//--------------------------------------------------------------
// RV32I ALU Operation Codes
//--------------------------------------------------------------

`define ALU_ADD    4'b0000
`define ALU_SUB    4'b0001
`define ALU_AND    4'b0010
`define ALU_OR     4'b0011
`define ALU_XOR    4'b0100
`define ALU_SLL    4'b0101
`define ALU_SRL    4'b0110
`define ALU_SRA    4'b0111
`define ALU_SLT    4'b1000
`define ALU_SLTU   4'b1001
`define ALU_PASS_B 4'b1010

`define OPCODE_OP 7'b0110011
`define OPCODE_OP_IMM   7'b0010011
`define OPCODE_LOAD     7'b0000011
`define OPCODE_STORE    7'b0100011
`define OPCODE_BRANCH   7'b1100011
`define OPCODE_LUI      7'b0110111
`define OPCODE_AUIPC    7'b0010111
`define OPCODE_JAL      7'b1101111
`define OPCODE_JALR     7'b1100111

`endif

rtl/common/rv32i_params.vh
`ifndef RV32I_PARAMS_VH
`define RV32I_PARAMS_VH

//==============================================================
// File        : rv32i_params.vh
// Description :
//   Global architectural parameters for the RV32I processor.
//
//   This file contains processor-wide constants that are shared
//   across multiple RTL modules.
//
//==============================================================

///////////////////////////////////////////////////////////////
// Processor Configuration
///////////////////////////////////////////////////////////////

`define XLEN                32
`define REG_COUNT           32
`define REG_ADDR_WIDTH      5

///////////////////////////////////////////////////////////////
// Program Counter
///////////////////////////////////////////////////////////////

`define RESET_VECTOR        32'h00000000
`define INSTRUCTION_SIZE    32'd4

///////////////////////////////////////////////////////////////
// Instruction Memory
///////////////////////////////////////////////////////////////

`define IMEM_DEPTH          1024

///////////////////////////////////////////////////////////////
// Data Memory
///////////////////////////////////////////////////////////////

`define DMEM_DEPTH          1024

///////////////////////////////////////////////////////////////
// SHA-256 Accelerator
///////////////////////////////////////////////////////////////

`define SHA_BLOCK_WIDTH     512
`define SHA_HASH_WIDTH      256

///////////////////////////////////////////////////////////////
// General Constants
///////////////////////////////////////////////////////////////

`define TRUE               1'b1
`define FALSE              1'b0

`endif

rtl/core/control_unit.v
`default_nettype none

`include "rv32i_params.vh"
`include "rv32i_defs.vh"

//==============================================================
// Module      : control_unit
// Description :
//   Main control unit for the RV32I processor.
//
//   Decodes the instruction opcode and generates the control
//   signals required to control the processor datapath.
//
// Control Signals:
//   - RegWrite : Enable register-file write
//   - MemRead  : Enable data-memory read
//   - MemWrite : Enable data-memory write
//   - MemToReg : Select memory data for register write-back
//   - ALUSrc   : Select ALU second operand
//   - Branch   : Indicates conditional branch
//   - Jump     : Indicates jump instruction
//   - ALUOp    : Selects ALU-control operation class
//
// Target FPGA : Xilinx Artix-7 (Basys-3)
//==============================================================

module control_unit (
    //----------------------------------------------------------
    // Instruction Opcode
    //----------------------------------------------------------

    input wire [6:0] opcode,

    //----------------------------------------------------------
    // Control Outputs
    //----------------------------------------------------------

    output reg       RegWrite,
    output reg       MemRead,
    output reg       MemWrite,
    output reg       MemToReg,
    output reg       ALUSrc,
    output reg       Branch,
    output reg       Jump,
    output reg [1:0] ALUOp
);

    //----------------------------------------------------------
    // Main Control Logic
    //----------------------------------------------------------

    always @(*) begin

        //------------------------------------------------------
        // Safe Default Values
        //------------------------------------------------------

        RegWrite = 1'b0;
        MemRead  = 1'b0;
        MemWrite = 1'b0;
        MemToReg = 1'b0;
        ALUSrc   = 1'b0;
        Branch   = 1'b0;
        Jump     = 1'b0;
        ALUOp    = 2'b00;

        //------------------------------------------------------
        // Opcode Decode
        //------------------------------------------------------

        case (opcode)

            //--------------------------------------------------
            // R-Type
            //
            // ADD, SUB, AND, OR, XOR, SLL, SRL, SRA,
            // SLT, SLTU
            //--------------------------------------------------

            `OPCODE_OP: begin

                RegWrite = 1'b1;
                ALUSrc   = 1'b0;
                ALUOp    = 2'b10;

            end

            //--------------------------------------------------
            // I-Type ALU
            //
            // ADDI, SLTI, SLTIU, XORI, ORI, ANDI,
            // SLLI, SRLI, SRAI
            //--------------------------------------------------

            `OPCODE_OP_IMM: begin

                RegWrite = 1'b1;
                ALUSrc   = 1'b1;
                ALUOp    = 2'b10;

            end

            //--------------------------------------------------
            // Load
            //
            // LB, LH, LW, LBU, LHU
            //--------------------------------------------------

            `OPCODE_LOAD: begin

                RegWrite = 1'b1;
                MemRead  = 1'b1;
                MemToReg = 1'b1;
                ALUSrc   = 1'b1;
                ALUOp    = 2'b00;

            end

            //--------------------------------------------------
            // Store
            //
            // SB, SH, SW
            //--------------------------------------------------

            `OPCODE_STORE: begin

                MemWrite = 1'b1;
                ALUSrc   = 1'b1;
                ALUOp    = 2'b00;

            end

            //--------------------------------------------------
            // Branch
            //
            // BEQ, BNE, BLT, BGE, BLTU, BGEU
            //--------------------------------------------------

            `OPCODE_BRANCH: begin

                Branch = 1'b1;
                ALUSrc = 1'b0;
                ALUOp  = 2'b01;

            end

            //--------------------------------------------------
            // LUI
            //--------------------------------------------------

            `OPCODE_LUI: begin

                RegWrite = 1'b1;
                ALUSrc   = 1'b1;
                ALUOp    = 2'b10;

            end

            //--------------------------------------------------
            // AUIPC
            //--------------------------------------------------

            `OPCODE_AUIPC: begin

                RegWrite = 1'b1;
                ALUSrc   = 1'b1;
                ALUOp    = 2'b10;

            end

            //--------------------------------------------------
            // JAL
            //--------------------------------------------------

            `OPCODE_JAL: begin

                RegWrite = 1'b1;
                Jump     = 1'b1;

            end

            //--------------------------------------------------
            // JALR
            //--------------------------------------------------

            `OPCODE_JALR: begin

                RegWrite = 1'b1;
                ALUSrc   = 1'b1;
                Jump     = 1'b1;
                ALUOp    = 2'b00;

            end

            //--------------------------------------------------
            // Unsupported Opcode
            //--------------------------------------------------

            default: begin

                // Safe defaults already assigned above.

            end

        endcase

    end

endmodule

`default_nettype wire

tb/core/control_unit_tb.v
`timescale 1ns/1ps
`default_nettype none

`include "rv32i_params.vh"
`include "rv32i_defs.vh"

//==============================================================
// Module      : control_unit_tb
// Description :
//   Self-checking testbench for the RV32I Main Control Unit.
//
//   Tests:
//   - R-Type
//   - I-Type ALU
//   - Load
//   - Store
//   - Branch
//   - LUI
//   - AUIPC
//   - JAL
//   - JALR
//   - Invalid opcode
//
//==============================================================

module control_unit_tb;

    //----------------------------------------------------------
    // DUT Signals
    //----------------------------------------------------------

    reg [6:0] opcode;

    wire       RegWrite;
    wire       MemRead;
    wire       MemWrite;
    wire       MemToReg;
    wire       ALUSrc;
    wire       Branch;
    wire       Jump;
    wire [1:0] ALUOp;

    //----------------------------------------------------------
    // Verification Statistics
    //----------------------------------------------------------

    integer tests;
    integer errors;

    //----------------------------------------------------------
    // Device Under Test
    //----------------------------------------------------------

    control_unit DUT (
        .opcode   (opcode),
        .RegWrite (RegWrite),
        .MemRead  (MemRead),
        .MemWrite (MemWrite),
        .MemToReg (MemToReg),
        .ALUSrc   (ALUSrc),
        .Branch   (Branch),
        .Jump     (Jump),
        .ALUOp    (ALUOp)
    );

    //----------------------------------------------------------
    // Waveform Dump
    //----------------------------------------------------------

    initial begin

        $dumpfile("sim/control_unit/control_unit.vcd");
        $dumpvars(0, control_unit_tb);

    end

    //----------------------------------------------------------
    // TASK : Check Control Signals
    //----------------------------------------------------------

    task check_control;

        input [6:0]  test_opcode;

        input        exp_RegWrite;
        input        exp_MemRead;
        input        exp_MemWrite;
        input        exp_MemToReg;
        input        exp_ALUSrc;
        input        exp_Branch;
        input        exp_Jump;
        input [1:0]  exp_ALUOp;

        input [127:0] test_name;

    begin

        //------------------------------------------------------
        // Apply Opcode
        //------------------------------------------------------

        opcode = test_opcode;

        #1;

        tests = tests + 1;

        //------------------------------------------------------
        // Compare Outputs
        //------------------------------------------------------

        if ((RegWrite !== exp_RegWrite) ||
            (MemRead  !== exp_MemRead ) ||
            (MemWrite !== exp_MemWrite) ||
            (MemToReg !== exp_MemToReg) ||
            (ALUSrc   !== exp_ALUSrc  ) ||
            (Branch   !== exp_Branch  ) ||
            (Jump     !== exp_Jump    ) ||
            (ALUOp    !== exp_ALUOp   )) begin

            $display("");
            $display("[FAIL] %s", test_name);

            $display("       Opcode   = %b", test_opcode);

            $display("       Expected:");
            $display("       RegWrite = %b", exp_RegWrite);
            $display("       MemRead  = %b", exp_MemRead);
            $display("       MemWrite = %b", exp_MemWrite);
            $display("       MemToReg = %b", exp_MemToReg);
            $display("       ALUSrc   = %b", exp_ALUSrc);
            $display("       Branch   = %b", exp_Branch);
            $display("       Jump     = %b", exp_Jump);
            $display("       ALUOp    = %b", exp_ALUOp);

            $display("       Actual:");
            $display("       RegWrite = %b", RegWrite);
            $display("       MemRead  = %b", MemRead);
            $display("       MemWrite = %b", MemWrite);
            $display("       MemToReg = %b", MemToReg);
            $display("       ALUSrc   = %b", ALUSrc);
            $display("       Branch   = %b", Branch);
            $display("       Jump     = %b", Jump);
            $display("       ALUOp    = %b", ALUOp);

            errors = errors + 1;

        end

        else begin

            $display("[PASS] %s", test_name);

        end

    end

    endtask

    //----------------------------------------------------------
    // Test Sequence
    //----------------------------------------------------------

    initial begin

        opcode = 7'b0000000;

        tests  = 0;
        errors = 0;

        #5;

        $display("");
        $display("=================================================");
        $display("        Main Control Unit Verification");
        $display("=================================================");

        //------------------------------------------------------
        // R-Type
        //------------------------------------------------------

        check_control(
            `OPCODE_OP,

            1'b1,       // RegWrite
            1'b0,       // MemRead
            1'b0,       // MemWrite
            1'b0,       // MemToReg
            1'b0,       // ALUSrc
            1'b0,       // Branch
            1'b0,       // Jump
            2'b10,      // ALUOp

            "R-Type"
        );

        //------------------------------------------------------
        // I-Type ALU
        //------------------------------------------------------

        check_control(
            `OPCODE_OP_IMM,

            1'b1,
            1'b0,
            1'b0,
            1'b0,
            1'b1,
            1'b0,
            1'b0,
            2'b10,

            "I-Type ALU"
        );

        //------------------------------------------------------
        // Load
        //------------------------------------------------------

        check_control(
            `OPCODE_LOAD,

            1'b1,
            1'b1,
            1'b0,
            1'b1,
            1'b1,
            1'b0,
            1'b0,
            2'b00,

            "Load"
        );

        //------------------------------------------------------
        // Store
        //------------------------------------------------------

        check_control(
            `OPCODE_STORE,

            1'b0,
            1'b0,
            1'b1,
            1'b0,
            1'b1,
            1'b0,
            1'b0,
            2'b00,

            "Store"
        );

        //------------------------------------------------------
        // Branch
        //------------------------------------------------------

        check_control(
            `OPCODE_BRANCH,

            1'b0,
            1'b0,
            1'b0,
            1'b0,
            1'b0,
            1'b1,
            1'b0,
            2'b01,

            "Branch"
        );

        //------------------------------------------------------
        // LUI
        //------------------------------------------------------

        check_control(
            `OPCODE_LUI,

            1'b1,
            1'b0,
            1'b0,
            1'b0,
            1'b1,
            1'b0,
            1'b0,
            2'b10,

            "LUI"
        );

        //------------------------------------------------------
        // AUIPC
        //------------------------------------------------------

        check_control(
            `OPCODE_AUIPC,

            1'b1,
            1'b0,
            1'b0,
            1'b0,
            1'b1,
            1'b0,
            1'b0,
            2'b10,

            "AUIPC"
        );

        //------------------------------------------------------
        // JAL
        //------------------------------------------------------

        check_control(
            `OPCODE_JAL,

            1'b1,
            1'b0,
            1'b0,
            1'b0,
            1'b0,
            1'b0,
            1'b1,
            2'b00,

            "JAL"
        );

        //------------------------------------------------------
        // JALR
        //------------------------------------------------------

        check_control(
            `OPCODE_JALR,

            1'b1,
            1'b0,
            1'b0,
            1'b0,
            1'b1,
            1'b0,
            1'b1,
            2'b00,

            "JALR"
        );

        //------------------------------------------------------
        // Invalid Opcode
        //------------------------------------------------------

        check_control(
            7'b1111111,

            1'b0,
            1'b0,
            1'b0,
            1'b0,
            1'b0,
            1'b0,
            1'b0,
            2'b00,

            "Invalid Opcode"
        );

        //------------------------------------------------------
        // Verification Summary
        //------------------------------------------------------

        $display("");
        $display("=================================================");
        $display("Verification Summary");
        $display("=================================================");

        $display("Tests  : %0d", tests);
        $display("Errors : %0d", errors);

        $display("");

        if (errors == 0) begin

            $display("***********************************************");
            $display("*                                             *");
            $display("*       ALL TESTS PASSED SUCCESSFULLY!       *");
            $display("*                                             *");
            $display("***********************************************");

        end

        else begin

            $display("***********************************************");
            $display("*                                             *");
            $display("*       VERIFICATION FAILED                   *");
            $display("*                                             *");
            $display("*       Errors : %0d                           *", errors);
            $display("*                                             *");
            $display("***********************************************");

        end

        $finish;

    end

endmodule

`default_nettype wire

sim/control_unit/control_unit.vcd
$date
	Sat Aug 08 14:13:03 2026
$end
$version
	Icarus Verilog
$end
$timescale
	1ps
$end
$scope module control_unit_tb $end
$var wire 1 ! RegWrite $end
$var wire 1 " MemWrite $end
$var wire 1 # MemToReg $end
$var wire 1 $ MemRead $end
$var wire 1 % Jump $end
$var wire 1 & Branch $end
$var wire 1 ' ALUSrc $end
$var wire 2 ( ALUOp [1:0] $end
$var reg 7 ) opcode [6:0] $end
$var integer 32 * errors [31:0] $end
$var integer 32 + tests [31:0] $end
$scope module DUT $end
$var wire 7 , opcode [6:0] $end
$var reg 2 - ALUOp [1:0] $end
$var reg 1 ' ALUSrc $end
$var reg 1 & Branch $end
$var reg 1 % Jump $end
$var reg 1 $ MemRead $end
$var reg 1 # MemToReg $end
$var reg 1 " MemWrite $end
$var reg 1 ! RegWrite $end
$upscope $end
$scope task check_control $end
$var reg 2 . exp_ALUOp [1:0] $end
$var reg 1 / exp_ALUSrc $end
$var reg 1 0 exp_Branch $end
$var reg 1 1 exp_Jump $end
$var reg 1 2 exp_MemRead $end
$var reg 1 3 exp_MemToReg $end
$var reg 1 4 exp_MemWrite $end
$var reg 1 5 exp_RegWrite $end
$var reg 128 6 test_name [127:0] $end
$var reg 7 7 test_opcode [6:0] $end
$upscope $end
$upscope $end
$enddefinitions $end
#0
$dumpvars
bx 7
bx 6
x5
x4
x3
x2
x1
x0
x/
bx .
b0 -
b0 ,
b0 +
b0 *
b0 )
b0 (
0'
0&
0%
0$
0#
0"
0!
$end
#5000
b10 (
b10 -
1!
b110011 )
b110011 ,
b10100100010110101010100011110010111000001100101 6
b10 .
01
00
0/
03
04
02
15
b110011 7
#6000
1'
b10 (
b10 -
1!
b10011 )
b10011 ,
b1001001001011010101010001111001011100000110010100100000010000010100110001010101 6
1/
b10011 7
b1 +
#7000
1#
1$
b0 (
b0 -
1'
1!
b11 )
b11 ,
b1001100011011110110000101100100 6
b0 .
13
12
b11 7
b10 +
#8000
1"
1'
0#
0$
0!
b100011 )
b100011 ,
b101001101110100011011110111001001100101 6
03
14
02
05
b100011 7
b11 +
#9000
b1 (
b1 -
1&
0'
0"
b1100011 )
b1100011 ,
b10000100111001001100001011011100110001101101000 6
b1 .
10
0/
04
b1100011 7
b100 +
#10000
1'
1!
b10 (
b10 -
0&
b110111 )
b110111 ,
b10011000101010101001001 6
b10 .
00
1/
15
b110111 7
b101 +
#11000
b10 (
b10 -
1'
1!
b10111 )
b10111 ,
b100000101010101010010010101000001000011 6
b10111 7
b110 +
#12000
1%
b0 (
b0 -
0'
1!
b1101111 )
b1101111 ,
b10010100100000101001100 6
b0 .
11
0/
b1101111 7
b111 +
#13000
1'
1%
1!
b1100111 )
b1100111 ,
b1001010010000010100110001010010 6
1/
b1100111 7
b1000 +
#14000
0%
0'
0!
b1111111 )
b1111111 ,
b100100101101110011101100110000101101100011010010110010000100000010011110111000001100011011011110110010001100101 6
01
0/
05
b1111111 7
b1001 +
#15000
b1010 +
